{
  "msg": "获取成功！",
  "code": 0,
  "data": {
    "totalCount": 2048,
    "datas": [
      {
        "id": "jwUBUz6tr9CNnFUiO9rsZKnxQOiUfr4AozJIPZKbMHc%3D",
        "cpws_al_id": "jwUBUz6tr9CNnFUiO9rsZKnxQOiUfr4AozJIPZKbMHc%3D",
        "cpws_al_type": "02",
        "cpws_al_status": "01",
        "cpws_al_fb_date": "",
        "cpws_al_no": "2024-18-1-207-009",
        "cpws_al_title": "柯某成侵犯公民个人信息案",
        "cpws_al_case_sort_id": [
          "01",
          "A01"
        ],
        "cpws_al_case_sort_name": "刑事",
        "cpws_al_sort_name": "侵犯公民个人信息罪",
        "cpws_al_slfy_name": "上海市金山区人民法院",
        "cpws_al_slfy_sf_name": "上海市",
        "cpws_al_zs_date": "2019.12.31",
        "cpws_al_ajzh": "（2018）沪0116刑初839号",
        "cpws_al_slcx_name": "一审",
        "cpws_al_cpyz": "　　<p>1.包含房产面积、价格等房产信息，且包含具体地址、门牌号码、房东姓名、电话等房东身份识别信息的房源信息，具有明确的指向性和可识别性，属于公民个人信息。<br/>　　2.对于仅供给中介提供服务使用的限定用途、范围的公民个人信息，在未经另行授权的情况下，他人非法获取、出售该信息，情节严重的，应当以侵犯公民个人信息罪定罪处罚。</p>",
        "cpws_al_fyjb_id": "",
        "cpws_al_fyjb_name": "",
        "cpws_al_spnf": "",
        "cpws_al_fbnf": "",
        "cpws_al_fulltext": "",
        "cpws_al_jbaq": "",
        "cpws_al_cpjg": "",
        "cpws_al_cply": "",
        "cpws_al_aljz": "",
        "cpws_al_glsy": "",
        "cpws_al_sub_title": "",
        "cpws_al_is_del": "",
        "cpws_al_infos": "2024-18-1-207-009 / 刑事 / 侵犯公民个人信息罪 / 上海市金山区人民法院 / 2019.12.31 / （2018）沪0116刑初839号 / 一审 / 入库日期：2024.12.24",
        "cpws_al_fbxx": "",
        "cpws_al_sxcpr": "",
        "cpws_al_pdls": "",
        "sort_num": "27714",
        "cpws_al_add_time": "",
        "cpws_al_rk_time": "2024-12-24 09:47:34",
        "cpws_al_update_time": "",
        "cpws_al_wsxz": "",
        "cpws_al_ts": "18",
        "cpws_al_ts_name": "（研究室）",
        "cpws_al_group": [],
        "cpws_al_sf": "上海市",
        "cpws_al_source_id": [
          "0101"
        ],
        "cpws_al_lzgc": "",
        "cpws_al_zdyy": "",
        "cpws_al_jdhg_id": "1321267587518050304",
        "ai_score": 0.0,
        "cpws_al_new_zdxal": ""
      },
      {
        "id": "ufsGYuyLQk7y6ZKCjO%2FZZzUdrUndN5ST52DBv%2B8uqUU%3D",
        "cpws_al_id": "ufsGYuyLQk7y6ZKCjO%2FZZzUdrUndN5ST52DBv%2B8uqUU%3D",
        "cpws_al_type": "02",
        "cpws_al_status": "01",
        "cpws_al_fb_date": "",
        "cpws_al_no": "2024-04-1-273-001",
        "cpws_al_title": "潘某卫纵容黑社会性质组织、受贿案",
        "cpws_al_case_sort_id": [
          "01",
          "A01"
        ],
        "cpws_al_case_sort_name": "刑事",
        "cpws_al_sort_name": "包庇、纵容黑社会性质组织罪",
        "cpws_al_slfy_name": "广东省江门市中级人民法院",
        "cpws_al_slfy_sf_name": "广东省",
        "cpws_al_zs_date": "2022.08.01",
        "cpws_al_ajzh": "（2022）粤07刑终198号",
        "cpws_al_slcx_name": "二审",
        "cpws_al_cpyz": "　　    1.纵容黑社会性质组织，同时符合纵容黑社会性质组织罪和徇私枉法罪构成要件的，应当按照处罚较重的规定定罪处罚。 <br/>　　    2.行为人收受贿赂及纵容黑社会性质组织进行违法犯罪活动的行为一直继续到《刑法修正案（八）》施行之后，应当适用刑法第二百九十四条第四款“犯前三款罪又有其他犯罪行为的，依照数罪并罚的规定处罚”的规定，以纵容黑社会性质组织罪、受贿罪数罪并罚。<br/>　　",
        "cpws_al_fyjb_id": "",
        "cpws_al_fyjb_name": "",
        "cpws_al_spnf": "",
        "cpws_al_fbnf": "",
        "cpws_al_fulltext": "",
        "cpws_al_jbaq": "",
        "cpws_al_cpjg": "",
        "cpws_al_cply": "",
        "cpws_al_aljz": "",
        "cpws_al_glsy": "",
        "cpws_al_sub_title": "",
        "cpws_al_is_del": "",
        "cpws_al_infos": "2024-04-1-273-001 / 刑事 / 包庇、纵容黑社会性质组织罪 / 广东省江门市中级人民法院 / 2022.08.01 / （2022）粤07刑终198号 / 二审 / 入库日期：2024.12.24",
        "cpws_al_fbxx": "",
        "cpws_al_sxcpr": "",
        "cpws_al_pdls": "",
        "sort_num": "27714",
        "cpws_al_add_time": "",
        "cpws_al_rk_time": "2024-12-24 09:05:42",
        "cpws_al_update_time": "",
        "cpws_al_wsxz": "",
        "cpws_al_ts": "04",
        "cpws_al_ts_name": "（刑三庭）",
        "cpws_al_sf": "广东省",
        "cpws_al_source_id": [
          "0101"
        ],
        "cpws_al_lzgc": "",
        "cpws_al_zdyy": "",
        "cpws_al_jdhg_id": "1212419431628550144",
        "ai_score": 0.0,
        "cpws_al_new_zdxal": ""
      },
      {
        "id": "U0pZdtthI7FntpOUllqIhOKzKcj9hsQ16hTuVgBZg5E%3D",
        "cpws_al_id": "U0pZdtthI7FntpOUllqIhOKzKcj9hsQ16hTuVgBZg5E%3D",
        "cpws_al_type": "02",
        "cpws_al_status": "01",
        "cpws_al_fb_date": "",
        "cpws_al_no": "2024-04-1-282-001",
        "cpws_al_title": "邵某、支某聚众淫乱、传播淫秽物品案",
        "cpws_al_case_sort_id": [
          "01",
          "A01"
        ],
        "cpws_al_case_sort_name": "刑事",
        "cpws_al_sort_name": "聚众淫乱罪",
        "cpws_al_slfy_name": "上海市第二中级人民法院",
        "cpws_al_slfy_sf_name": "上海市",
        "cpws_al_zs_date": "2021.12.15",
        "cpws_al_ajzh": "（2021）沪02刑终1145号",
        "cpws_al_slcx_name": "二审",
        "cpws_al_cpyz": "　　<p>在互联网上发布淫秽物品，招募他人共同参与聚众淫乱活动的，一方面传播淫秽物品通过互联网向不特定人传播,有损不特定公众的身心健康，严重破坏社会管理秩序；另一方面聚众淫乱违背传统伦理道德观念，严重破坏公序良俗。鉴于两个行为所侵害法益并不相同，应当分别评价、独立构成犯罪，以传播淫秽物品罪与聚众淫乱罪进行并罚。</p>",
        "cpws_al_fyjb_id": "",
        "cpws_al_fyjb_name": "",
        "cpws_al_spnf": "",
        "cpws_al_fbnf": "",
        "cpws_al_fulltext": "",
        "cpws_al_jbaq": "",
        "cpws_al_cpjg": "",
        "cpws_al_cply": "",
        "cpws_al_aljz": "",
        "cpws_al_glsy": "",
        "cpws_al_sub_title": "",
        "cpws_al_is_del": "",
        "cpws_al_infos": "2024-04-1-282-001 / 刑事 / 聚众淫乱罪 / 上海市第二中级人民法院 / 2021.12.15 / （2021）沪02刑终1145号 / 二审 / 入库日期：2024.12.23 / 修改日期：2025.01.02",
        "cpws_al_fbxx": "",
        "cpws_al_sxcpr": "",
        "cpws_al_pdls": "",
        "sort_num": "27711",
        "cpws_al_add_time": "",
        "cpws_al_rk_time": "2024-12-23 19:30:06",
        "cpws_al_update_time": "2025-01-02 10:02:06",
        "cpws_al_wsxz": "",
        "cpws_al_ts": "04",
        "cpws_al_ts_name": "（刑三庭）",
        "cpws_al_group": [],
        "cpws_al_sf": "上海市",
        "cpws_al_source_id": [
          "0101"
        ],
        "cpws_al_lzgc": "",
        "cpws_al_zdyy": "",
        "cpws_al_jdhg_id": "1320905253159186432",
        "ai_score": 0.0,
        "cpws_al_new_zdxal": ""
      },
      {
        "id": "p%2FgZcad9cirXAtYqjnla8unYBHq9Vm9krAdk3Dmbv3s%3D",
        "cpws_al_id": "p%2FgZcad9cirXAtYqjnla8unYBHq9Vm9krAdk3Dmbv3s%3D",
        "cpws_al_type": "02",
        "cpws_al_status": "01",
        "cpws_al_fb_date": "",
        "cpws_al_no": "2024-18-1-222-004",
        "cpws_al_title": "周某仁等人诈骗案",
        "cpws_al_case_sort_id": [
          "01",
          "A01"
        ],
        "cpws_al_case_sort_name": "刑事",
        "cpws_al_sort_name": "诈骗罪",
        "cpws_al_slfy_name": "浙江省绍兴市中级人民法院",
        "cpws_al_slfy_sf_name": "浙江省",
        "cpws_al_zs_date": "2022.09.13",
        "cpws_al_ajzh": "（2022）浙06刑终258号",
        "cpws_al_slcx_name": "二审",
        "cpws_al_cpyz": "　　<p>行为人虚构享有著作权的事实进行“维权”提起民事诉讼，符合刑法第三百零七条之一规定的，以虚假诉讼罪定罪处罚；同时构成其他犯罪的，依照处罚较重的规定定罪从重处罚。</p>",
        "cpws_al_fyjb_id": "",
        "cpws_al_fyjb_name": "",
        "cpws_al_spnf": "",
        "cpws_al_fbnf": "",
        "cpws_al_fulltext": "",
        "cpws_al_jbaq": "",
        "cpws_al_cpjg": "",
        "cpws_al_cply": "",
        "cpws_al_aljz": "",
        "cpws_al_glsy": "",
        "cpws_al_sub_title": "",
        "cpws_al_is_del": "",
        "cpws_al_infos": "2024-18-1-222-004 / 刑事 / 诈骗罪 / 浙江省绍兴市中级人民法院 / 2022.09.13 / （2022）浙06刑终258号 / 二审 / 入库日期：2024.12.23",
        "cpws_al_fbxx": "",
        "cpws_al_sxcpr": "",
        "cpws_al_pdls": "",
        "sort_num": "27705",
        "cpws_al_add_time": "",
        "cpws_al_rk_time": "2024-12-23 19:06:04",
        "cpws_al_update_time": "",
        "cpws_al_wsxz": "",
        "cpws_al_ts": "18",
        "cpws_al_ts_name": "（研究室）",
        "cpws_al_group": [],
        "cpws_al_sf": "浙江省",
        "cpws_al_source_id": [
          "0101"
        ],
        "cpws_al_lzgc": "",
        "cpws_al_zdyy": "",
        "cpws_al_jdhg_id": "1320905247194886144",
        "ai_score": 0.0,
        "cpws_al_new_zdxal": ""
      },
      {
        "id": "V0UwqN5vIDOH6NonUsI8rxipyI3XYtkGvrDmK6%2BFOwc%3D",
        "cpws_al_id": "V0UwqN5vIDOH6NonUsI8rxipyI3XYtkGvrDmK6%2BFOwc%3D",
        "cpws_al_type": "02",
        "cpws_al_status": "01",
        "cpws_al_fb_date": "",
        "cpws_al_no": "2024-18-1-134-001",
        "cpws_al_title": "周某集资诈骗案",
        "cpws_al_case_sort_id": [
          "01",
          "A01"
        ],
        "cpws_al_case_sort_name": "刑事",
        "cpws_al_sort_name": "集资诈骗罪",
        "cpws_al_slfy_name": "浙江省高级人民法院",
        "cpws_al_slfy_sf_name": "浙江省",
        "cpws_al_zs_date": "2016.04.29",
        "cpws_al_ajzh": "（2015）浙刑二终字第104号",
        "cpws_al_slcx_name": "二审",
        "cpws_al_cpyz": "　　<p>未经有关部门批准，网络借贷信息中介机构或其控制人，利用网络借贷平台发布虚假信息，非法建立资金池募集资金，所得资金大部分未用于生产经营活动，主要用于借新还旧和个人挥霍，无法归还所募资金数额巨大的，应当认定为具有非法占有目的，符合《中华人民共和国刑法》第一百九十二条规定的，以集资诈骗罪追究刑事责任。</p>",
        "cpws_al_fyjb_id": "",
        "cpws_al_fyjb_name": "",
        "cpws_al_spnf": "",
        "cpws_al_fbnf": "",
        "cpws_al_fulltext": "",
        "cpws_al_jbaq": "",
        "cpws_al_cpjg": "",
        "cpws_al_cply": "",
        "cpws_al_aljz": "",
        "cpws_al_glsy": "",
        "cpws_al_sub_title": "",
        "cpws_al_is_del": "",
        "cpws_al_infos": "2024-18-1-134-001 / 刑事 / 集资诈骗罪 / 浙江省高级人民法院 / 2016.04.29 / （2015）浙刑二终字第104号 / 二审 / 入库日期：2024.12.23",
        "cpws_al_fbxx": "",
        "cpws_al_sxcpr": "",
        "cpws_al_pdls": "",
        "sort_num": "27702",
        "cpws_al_add_time": "",
        "cpws_al_rk_time": "2024-12-23 19:04:29",
        "cpws_al_update_time": "",
        "cpws_al_wsxz": "",
        "cpws_al_ts": "18",
        "cpws_al_ts_name": "（研究室）",
        "cpws_al_group": [],
        "cpws_al_sf": "浙江省",
        "cpws_al_source_id": [
          "0101"
        ],
        "cpws_al_lzgc": "",
        "cpws_al_zdyy": "",
        "cpws_al_jdhg_id": "1320905244544086016",
        "ai_score": 0.0,
        "cpws_al_new_zdxal": ""
      },
      {
        "id": "r5cZoBDs5FySrCbpc0R9uoaODBy1nPM8ugd6ihpbOME%3D",
        "cpws_al_id": "r5cZoBDs5FySrCbpc0R9uoaODBy1nPM8ugd6ihpbOME%3D",
        "cpws_al_type": "02",
        "cpws_al_status": "01",
        "cpws_al_fb_date": "",
        "cpws_al_no": "2024-18-1-253-002",
        "cpws_al_title": "叶某星、张某秋提供侵入计算机信息系统程序、谭某妹非法获取计算机信息系统数据案系统案",
        "cpws_al_case_sort_id": [
          "01",
          "A01"
        ],
        "cpws_al_case_sort_name": "刑事",
        "cpws_al_sort_name": "提供侵入、非法控制计算机信息系统程序、工具罪",
        "cpws_al_slfy_name": "杭州市余杭区人民法院",
        "cpws_al_slfy_sf_name": "浙江省",
        "cpws_al_zs_date": "2018.05.18",
        "cpws_al_ajzh": "（2017）浙0110刑初664号",
        "cpws_al_slcx_name": "一审",
        "cpws_al_cpyz": "　　<p>1.对有证据证明用途单一，只能用于侵入计算机信息系统的程序，司法机关可依法认定为“专门用于侵入计算机信息系统的程序”；难以确定的，应当委托专门部门或司法鉴定机构作出检验或鉴定。<br/>　　2.图片验证码识别平台与侵入计算机信息系统程序共同实现侵入他人计算机信息系统的功能，对于该平台的组织运营者，应当依照提供侵入计算机信息系统程序共同犯罪论处。</p>",
        "cpws_al_fyjb_id": "",
        "cpws_al_fyjb_name": "",
        "cpws_al_spnf": "",
        "cpws_al_fbnf": "",
        "cpws_al_fulltext": "",
        "cpws_al_jbaq": "",
        "cpws_al_cpjg": "",
        "cpws_al_cply": "",
        "cpws_al_aljz": "",
        "cpws_al_glsy": "",
        "cpws_al_sub_title": "",
        "cpws_al_is_del": "",
        "cpws_al_infos": "2024-18-1-253-002 / 刑事 / 提供侵入、非法控制计算机信息系统程序、工具罪 / 杭州市余杭区人民法院 / 2018.05.18 / （2017）浙0110刑初664号 / 一审 / 入库日期：2024.12.23",
        "cpws_al_fbxx": "",
        "cpws_al_sxcpr": "",
        "cpws_al_pdls": "",
        "sort_num": "27699",
        "cpws_al_add_time": "",
        "cpws_al_rk_time": "2024-12-23 19:03:10",
        "cpws_al_update_time": "",
        "cpws_al_wsxz": "",
        "cpws_al_ts": "18",
        "cpws_al_ts_name": "（研究室）",
        "cpws_al_group": [],
        "cpws_al_sf": "浙江省",
        "cpws_al_source_id": [
          "0101"
        ],
        "cpws_al_lzgc": "",
        "cpws_al_zdyy": "",
        "cpws_al_jdhg_id": "1320905241310277632",
        "ai_score": 0.0,
        "cpws_al_new_zdxal": ""
      },
      {
        "id": "fhZNiD1IrqGF%2FSjCponBXfEZ7Y37hUniuTgbsCwFQu4%3D",
        "cpws_al_id": "fhZNiD1IrqGF%2FSjCponBXfEZ7Y37hUniuTgbsCwFQu4%3D",
        "cpws_al_type": "02",
        "cpws_al_status": "01",
        "cpws_al_fb_date": "",
        "cpws_al_no": "2024-18-1-168-001",
        "cpws_al_title": "叶某生、叶某松组织、领导传销活动案",
        "cpws_al_case_sort_id": [
          "01",
          "A01"
        ],
        "cpws_al_case_sort_name": "刑事",
        "cpws_al_sort_name": "组织、领导传销活动罪",
        "cpws_al_slfy_name": "浙江省丽水市中级人民法院",
        "cpws_al_slfy_sf_name": "浙江省",
        "cpws_al_zs_date": "2013.12.20",
        "cpws_al_ajzh": "（2013）浙丽刑终字第129号",
        "cpws_al_slcx_name": "二审",
        "cpws_al_cpyz": "　　<p>组织者、经营者利用互联网平台，要求参加者以缴纳入门费或者购买商品、服务等方式获取会员资格，并按一定顺序发展层级关系，直接或间接以发展人员数量或下线销售业绩作为计酬或者返利依据，引诱、胁迫参加者继续发展下线，骗取财物，扰乱市场经济秩序，符合《中华人民共和国刑法》第二百二十四条之一的，应当以组织、领导传销活动罪论处。</p>",
        "cpws_al_fyjb_id": "",
        "cpws_al_fyjb_name": "",
        "cpws_al_spnf": "",
        "cpws_al_fbnf": "",
        "cpws_al_fulltext": "",
        "cpws_al_jbaq": "",
        "cpws_al_cpjg": "",
        "cpws_al_cply": "",
        "cpws_al_aljz": "",
        "cpws_al_glsy": "",
        "cpws_al_sub_title": "",
        "cpws_al_is_del": "",
        "cpws_al_infos": "2024-18-1-168-001 / 刑事 / 组织、领导传销活动罪 / 浙江省丽水市中级人民法院 / 2013.12.20 / （2013）浙丽刑终字第129号 / 二审 / 入库日期：2024.12.23",
        "cpws_al_fbxx": "",
        "cpws_al_sxcpr": "",
        "cpws_al_pdls": "",
        "sort_num": "27696",
        "cpws_al_add_time": "",
        "cpws_al_rk_time": "2024-12-23 19:01:43",
        "cpws_al_update_time": "",
        "cpws_al_wsxz": "",
        "cpws_al_ts": "18",
        "cpws_al_ts_name": "（研究室）",
        "cpws_al_group": [],
        "cpws_al_sf": "浙江省",
        "cpws_al_source_id": [
          "0101"
        ],
        "cpws_al_lzgc": "",
        "cpws_al_zdyy": "",
        "cpws_al_jdhg_id": "1320905238583980032",
        "ai_score": 0.0,
        "cpws_al_new_zdxal": ""
      },
      {
        "id": "AqfLRmfKeCHDYyzQ6dVCgiUUKq%2Fwrjik78aZ8qLANug%3D",
        "cpws_al_id": "AqfLRmfKeCHDYyzQ6dVCgiUUKq%2Fwrjik78aZ8qLANug%3D",
        "cpws_al_type": "02",
        "cpws_al_status": "01",
        "cpws_al_fb_date": "",
        "cpws_al_no": "2024-18-1-222-003",
        "cpws_al_title": "姚某涛等诈骗案",
        "cpws_al_case_sort_id": [
          "01",
          "A01"
        ],
        "cpws_al_case_sort_name": "刑事",
        "cpws_al_sort_name": "诈骗罪",
        "cpws_al_slfy_name": "浙江省台州市中级人民法院",
        "cpws_al_slfy_sf_name": "浙江省",
        "cpws_al_zs_date": "2020.12.07",
        "cpws_al_ajzh": "（2020）浙10刑终454号",
        "cpws_al_slcx_name": "二审",
        "cpws_al_cpyz": "　　<p>以提供高息回报金融产品、高薪兼职工作等为手段进行诈骗兼具诈骗罪和传销犯罪的特征。对此，应当通过区分被害人主观认识、客观方面以及犯罪集团经营组织模式等方面进行研判。主观方面，被害人交纳会员费是为了获得高薪兼职工作，并非为了加入犯罪集团。客观方面，犯罪集团声称的提供高薪兼职工作并不存在，属于虚构事实的诈骗。从犯罪集团组织模式看，其内部没有形成拉人头式的层级，收入来源就是会员交纳的会员费。对于所涉行为具有非法占有目的，虚构事实骗取财物的，依法以诈骗罪论处。</p>",
        "cpws_al_fyjb_id": "",
        "cpws_al_fyjb_name": "",
        "cpws_al_spnf": "",
        "cpws_al_fbnf": "",
        "cpws_al_fulltext": "",
        "cpws_al_jbaq": "",
        "cpws_al_cpjg": "",
        "cpws_al_cply": "",
        "cpws_al_aljz": "",
        "cpws_al_glsy": "",
        "cpws_al_sub_title": "",
        "cpws_al_is_del": "",
        "cpws_al_infos": "2024-18-1-222-003 / 刑事 / 诈骗罪 / 浙江省台州市中级人民法院 / 2020.12.07 / （2020）浙10刑终454号 / 二审 / 入库日期：2024.12.23",
        "cpws_al_fbxx": "",
        "cpws_al_sxcpr": "",
        "cpws_al_pdls": "",
        "sort_num": "27693",
        "cpws_al_add_time": "",
        "cpws_al_rk_time": "2024-12-23 19:00:22",
        "cpws_al_update_time": "",
        "cpws_al_wsxz": "",
        "cpws_al_ts": "18",
        "cpws_al_ts_name": "（研究室）",
        "cpws_al_group": [],
        "cpws_al_sf": "浙江省",
        "cpws_al_source_id": [
          "0101"
        ],
        "cpws_al_lzgc": "",
        "cpws_al_zdyy": "",
        "cpws_al_jdhg_id": "1320905235610218496",
        "ai_score": 0.0,
        "cpws_al_new_zdxal": ""
      },
      {
        "id": "kO1gtVhFUI2K4M6mHtgaSBhQtVdbw%2FJUu%2BNCJS7RiRU%3D",
        "cpws_al_id": "kO1gtVhFUI2K4M6mHtgaSBhQtVdbw%2FJUu%2BNCJS7RiRU%3D",
        "cpws_al_type": "02",
        "cpws_al_status": "01",
        "cpws_al_fb_date": "",
        "cpws_al_no": "2024-18-1-177-005",
        "cpws_al_title": "陈某故意杀人再审宣告无罪案",
        "cpws_al_case_sort_id": [
          "01",
          "A01"
        ],
        "cpws_al_case_sort_name": "刑事",
        "cpws_al_sort_name": "故意杀人罪",
        "cpws_al_slfy_name": "浙江省高级人民法院",
        "cpws_al_slfy_sf_name": "浙江省",
        "cpws_al_zs_date": "2016.01.25",
        "cpws_al_ajzh": "（2015）浙刑再字第2号",
        "cpws_al_slcx_name": "再审",
        "cpws_al_cpyz": "　　<p>对于在案发现场提取的物证等实物证据，未经鉴定，且在诉讼过程中丢失或者毁灭，无法在庭审中出示、质证的，不能作为定案的根据。有罪供述的客观性、真实性存疑，且无其他经依法查证属实的证据相印证的，不能认定被告人有罪并判处刑罚。</p>",
        "cpws_al_fyjb_id": "",
        "cpws_al_fyjb_name": "",
        "cpws_al_spnf": "",
        "cpws_al_fbnf": "",
        "cpws_al_fulltext": "",
        "cpws_al_jbaq": "",
        "cpws_al_cpjg": "",
        "cpws_al_cply": "",
        "cpws_al_aljz": "",
        "cpws_al_glsy": "",
        "cpws_al_sub_title": "",
        "cpws_al_is_del": "",
        "cpws_al_infos": "2024-18-1-177-005 / 刑事 / 故意杀人罪 / 浙江省高级人民法院 / 2016.01.25 / （2015）浙刑再字第2号 / 再审 / 入库日期：2024.12.23",
        "cpws_al_fbxx": "",
        "cpws_al_sxcpr": "",
        "cpws_al_pdls": "",
        "sort_num": "27687",
        "cpws_al_add_time": "",
        "cpws_al_rk_time": "2024-12-23 18:47:18",
        "cpws_al_update_time": "",
        "cpws_al_wsxz": "",
        "cpws_al_ts": "18",
        "cpws_al_ts_name": "（研究室）",
        "cpws_al_group": [],
        "cpws_al_sf": "浙江省",
        "cpws_al_source_id": [
          "0101"
        ],
        "cpws_al_lzgc": "",
        "cpws_al_zdyy": "",
        "cpws_al_jdhg_id": "1320905230035988480",
        "ai_score": 0.0,
        "cpws_al_new_zdxal": ""
      },
      {
        "id": "ms0aNHPL7LPa7At3BvMOgp%2Fe5JLuhEgOxVBGMHMLC9I%3D",
        "cpws_al_id": "ms0aNHPL7LPa7At3BvMOgp%2Fe5JLuhEgOxVBGMHMLC9I%3D",
        "cpws_al_type": "02",
        "cpws_al_status": "01",
        "cpws_al_fb_date": "",
        "cpws_al_no": "2024-18-1-213-003",
        "cpws_al_title": "段某军破坏军婚案",
        "cpws_al_case_sort_id": [
          "01",
          "A01"
        ],
        "cpws_al_case_sort_name": "刑事",
        "cpws_al_sort_name": "破坏军婚罪",
        "cpws_al_slfy_name": "内蒙古自治区乌兰察布市中级人民法院",
        "cpws_al_slfy_sf_name": "内蒙古自治区",
        "cpws_al_zs_date": "2023.05.30",
        "cpws_al_ajzh": "（2023）内09刑终75号",
        "cpws_al_slcx_name": "二审",
        "cpws_al_cpyz": "　　<p>对于破坏军婚案件，现役军人提出控告，而公安机关或者人民检察院不予追究行为人刑事责任的，现役军人可以依法向人民法院提起自诉；经审查，符合自诉案件受理条件的，人民法院应当依法审理。</p>",
        "cpws_al_fyjb_id": "",
        "cpws_al_fyjb_name": "",
        "cpws_al_spnf": "",
        "cpws_al_fbnf": "",
        "cpws_al_fulltext": "",
        "cpws_al_jbaq": "",
        "cpws_al_cpjg": "",
        "cpws_al_cply": "",
        "cpws_al_aljz": "",
        "cpws_al_glsy": "",
        "cpws_al_sub_title": "",
        "cpws_al_is_del": "",
        "cpws_al_infos": "2024-18-1-213-003 / 刑事 / 破坏军婚罪 / 内蒙古自治区乌兰察布市中级人民法院 / 2023.05.30 / （2023）内09刑终75号 / 二审 / 入库日期：2024.12.23",
        "cpws_al_fbxx": "",
        "cpws_al_sxcpr": "",
        "cpws_al_pdls": "",
        "sort_num": "27684",
        "cpws_al_add_time": "",
        "cpws_al_rk_time": "2024-12-23 18:12:34",
        "cpws_al_update_time": "",
        "cpws_al_wsxz": "",
        "cpws_al_ts": "18",
        "cpws_al_ts_name": "（研究室）",
        "cpws_al_group": [],
        "cpws_al_sf": "内蒙古自治区",
        "cpws_al_source_id": [
          "0101"
        ],
        "cpws_al_lzgc": "",
        "cpws_al_zdyy": "",
        "cpws_al_jdhg_id": "1320905227511017472",
        "ai_score": 0.0,
        "cpws_al_new_zdxal": ""
      },
      {
        "id": "nU5dMx6WefRQgdd%2B7uD2SMyNxHzGZ7W5OjT5xNWr20A%3D",
        "cpws_al_id": "nU5dMx6WefRQgdd%2B7uD2SMyNxHzGZ7W5OjT5xNWr20A%3D",
        "cpws_al_type": "02",
        "cpws_al_status": "01",
        "cpws_al_fb_date": "",
        "cpws_al_no": "2024-18-1-213-002",
        "cpws_al_title": "骆某飞破坏军婚案",
        "cpws_al_case_sort_id": [
          "01",
          "A01"
        ],
        "cpws_al_case_sort_name": "刑事",
        "cpws_al_sort_name": "破坏军婚罪",
        "cpws_al_slfy_name": "杭州市富阳区人民法院",
        "cpws_al_slfy_sf_name": "浙江省",
        "cpws_al_zs_date": "2019.01.15",
        "cpws_al_ajzh": "（2019）浙0111刑初5号",
        "cpws_al_slcx_name": "一审",
        "cpws_al_cpyz": "　　<p>行为人明知是现役军人配偶，仍与其建立情人关系，常态化出入其住处，与其多次发生不正当两性关系，并建立经济、生活上的紧密联系的，应当认定为刑法第二百五十九条第一款规定的“同居”。</p>",
        "cpws_al_fyjb_id": "",
        "cpws_al_fyjb_name": "",
        "cpws_al_spnf": "",
        "cpws_al_fbnf": "",
        "cpws_al_fulltext": "",
        "cpws_al_jbaq": "",
        "cpws_al_cpjg": "",
        "cpws_al_cply": "",
        "cpws_al_aljz": "",
        "cpws_al_glsy": "",
        "cpws_al_sub_title": "",
        "cpws_al_is_del": "",
        "cpws_al_infos": "2024-18-1-213-002 / 刑事 / 破坏军婚罪 / 杭州市富阳区人民法院 / 2019.01.15 / （2019）浙0111刑初5号 / 一审 / 入库日期：2024.12.23",
        "cpws_al_fbxx": "",
        "cpws_al_sxcpr": "",
        "cpws_al_pdls": "",
        "sort_num": "27681",
        "cpws_al_add_time": "",
        "cpws_al_rk_time": "2024-12-23 18:05:20",
        "cpws_al_update_time": "",
        "cpws_al_wsxz": "",
        "cpws_al_ts": "18",
        "cpws_al_ts_name": "（研究室）",
        "cpws_al_group": [],
        "cpws_al_sf": "浙江省",
        "cpws_al_source_id": [
          "0101"
        ],
        "cpws_al_lzgc": "",
        "cpws_al_zdyy": "",
        "cpws_al_jdhg_id": "1320905224705028096",
        "ai_score": 0.0,
        "cpws_al_new_zdxal": ""
      },
      {
        "id": "sZ%2FU9z3e9DQJ3xkfANxGkuzSpOGD2bAeEPULVUKUF3w%3D",
        "cpws_al_id": "sZ%2FU9z3e9DQJ3xkfANxGkuzSpOGD2bAeEPULVUKUF3w%3D",
        "cpws_al_type": "02",
        "cpws_al_status": "01",
        "cpws_al_fb_date": "",
        "cpws_al_no": "2024-18-1-213-001",
        "cpws_al_title": "郑某寿破坏军婚案",
        "cpws_al_case_sort_id": [
          "01",
          "A01"
        ],
        "cpws_al_case_sort_name": "刑事",
        "cpws_al_sort_name": "破坏军婚罪",
        "cpws_al_slfy_name": "浙江省杭州市中级人民法院",
        "cpws_al_slfy_sf_name": "浙江省",
        "cpws_al_zs_date": "2024.07.31",
        "cpws_al_ajzh": "（2024）浙01刑终410号",
        "cpws_al_slcx_name": "二审",
        "cpws_al_cpyz": "　　<p>行为人与现役军人的配偶之间存在长期、多次发生性关系、居住场所相对固定、经济上相互支持、生活上相互照顾等情节的，应当认定二人达到了持续、稳定的共同生活的程度，属于刑法第二百五十九条第一款规定的“同居”。</p>",
        "cpws_al_fyjb_id": "",
        "cpws_al_fyjb_name": "",
        "cpws_al_spnf": "",
        "cpws_al_fbnf": "",
        "cpws_al_fulltext": "",
        "cpws_al_jbaq": "",
        "cpws_al_cpjg": "",
        "cpws_al_cply": "",
        "cpws_al_aljz": "",
        "cpws_al_glsy": "",
        "cpws_al_sub_title": "",
        "cpws_al_is_del": "",
        "cpws_al_infos": "2024-18-1-213-001 / 刑事 / 破坏军婚罪 / 浙江省杭州市中级人民法院 / 2024.07.31 / （2024）浙01刑终410号 / 二审 / 入库日期：2024.12.23",
        "cpws_al_fbxx": "",
        "cpws_al_sxcpr": "",
        "cpws_al_pdls": "",
        "sort_num": "27678",
        "cpws_al_add_time": "",
        "cpws_al_rk_time": "2024-12-23 17:59:13",
        "cpws_al_update_time": "",
        "cpws_al_wsxz": "",
        "cpws_al_ts": "18",
        "cpws_al_ts_name": "（研究室）",
        "cpws_al_group": [],
        "cpws_al_sf": "浙江省",
        "cpws_al_source_id": [
          "0101"
        ],
        "cpws_al_lzgc": "",
        "cpws_al_zdyy": "",
        "cpws_al_jdhg_id": "1320905220137431040",
        "ai_score": 0.0,
        "cpws_al_new_zdxal": ""
      },
      {
        "id": "MUuetReEYCmhPUgjScGLQbUtR73hgFKzdxQplBiZOC0%3D",
        "cpws_al_id": "MUuetReEYCmhPUgjScGLQbUtR73hgFKzdxQplBiZOC0%3D",
        "cpws_al_type": "02",
        "cpws_al_status": "01",
        "cpws_al_fb_date": "",
        "cpws_al_no": "2024-03-1-172-001",
        "cpws_al_title": "王某强、王某倒卖车票案",
        "cpws_al_case_sort_id": [
          "01",
          "A01"
        ],
        "cpws_al_case_sort_name": "刑事",
        "cpws_al_sort_name": "倒卖车票、船票罪",
        "cpws_al_slfy_name": "哈尔滨铁路运输中级法院",
        "cpws_al_slfy_sf_name": "黑龙江省",
        "cpws_al_zs_date": "2021.12.31",
        "cpws_al_ajzh": "（2021）黑71刑终11号",
        "cpws_al_slcx_name": "二审",
        "cpws_al_cpyz": "　　社会人员与铁路车站售票员勾结，利用售票员的职务便利占票、退票，并使用抢票软件采取不间断刷新抢票、重复提交订单购票等方式抢购火车票，之后加价倒卖，数量多、金额巨大的，应当以倒卖车票罪论处。<br/>　　",
        "cpws_al_fyjb_id": "",
        "cpws_al_fyjb_name": "",
        "cpws_al_spnf": "",
        "cpws_al_fbnf": "",
        "cpws_al_fulltext": "",
        "cpws_al_jbaq": "",
        "cpws_al_cpjg": "",
        "cpws_al_cply": "",
        "cpws_al_aljz": "",
        "cpws_al_glsy": "",
        "cpws_al_sub_title": "",
        "cpws_al_is_del": "",
        "cpws_al_infos": "2024-03-1-172-001 / 刑事 / 倒卖车票、船票罪 / 哈尔滨铁路运输中级法院 / 2021.12.31 / （2021）黑71刑终11号 / 二审 / 入库日期：2024.12.23",
        "cpws_al_fbxx": "",
        "cpws_al_sxcpr": "",
        "cpws_al_pdls": "",
        "sort_num": "27678",
        "cpws_al_add_time": "",
        "cpws_al_rk_time": "2024-12-23 13:34:54",
        "cpws_al_update_time": "",
        "cpws_al_wsxz": "",
        "cpws_al_ts": "03",
        "cpws_al_ts_name": "（刑二庭）",
        "cpws_al_sf": "黑龙江省",
        "cpws_al_source_id": [
          "0101"
        ],
        "cpws_al_lzgc": "",
        "cpws_al_zdyy": "",
        "cpws_al_jdhg_id": "1210160589771382784",
        "ai_score": 0.0,
        "cpws_al_new_zdxal": ""
      },
      {
        "id": "Z%2FQvOrQlNnjAmhyoLCUy09sjtqHsuEPnvHBlwvwhSMQ%3D",
        "cpws_al_id": "Z%2FQvOrQlNnjAmhyoLCUy09sjtqHsuEPnvHBlwvwhSMQ%3D",
        "cpws_al_type": "02",
        "cpws_al_status": "01",
        "cpws_al_fb_date": "",
        "cpws_al_no": "2024-05-1-282-001",
        "cpws_al_title": "王某旭、杨某田等聚众淫乱案",
        "cpws_al_case_sort_id": [
          "01",
          "A01"
        ],
        "cpws_al_case_sort_name": "刑事",
        "cpws_al_sort_name": "聚众淫乱罪",
        "cpws_al_slfy_name": "重庆市第五中级人民法院",
        "cpws_al_slfy_sf_name": "重庆市",
        "cpws_al_zs_date": "2020.10.22",
        "cpws_al_ajzh": "（2020）渝05刑终740号",
        "cpws_al_slcx_name": "二审",
        "cpws_al_cpyz": "　　    行为人采取拉拢腐蚀、蛊惑人心、煽情刺激等手段，将不特定多人纠集在一起进行淫乱活动，并负责规划聚众淫乱方案、联系参与人员、提供淫乱场所、指导淫乱活动过程、录制淫乱视频等的，系在聚众淫乱中起组织、策划、指挥作用的人，应当认定为聚众进行淫乱活动的“首要分子”。<br/>　　",
        "cpws_al_fyjb_id": "",
        "cpws_al_fyjb_name": "",
        "cpws_al_spnf": "",
        "cpws_al_fbnf": "",
        "cpws_al_fulltext": "",
        "cpws_al_jbaq": "",
        "cpws_al_cpjg": "",
        "cpws_al_cply": "",
        "cpws_al_aljz": "",
        "cpws_al_glsy": "",
        "cpws_al_sub_title": "",
        "cpws_al_is_del": "",
        "cpws_al_infos": "2024-05-1-282-001 / 刑事 / 聚众淫乱罪 / 重庆市第五中级人民法院 / 2020.10.22 / （2020）渝05刑终740号 / 二审 / 入库日期：2024.12.23",
        "cpws_al_fbxx": "",
        "cpws_al_sxcpr": "",
        "cpws_al_pdls": "",
        "sort_num": "27678",
        "cpws_al_add_time": "",
        "cpws_al_rk_time": "2024-12-23 13:34:53",
        "cpws_al_update_time": "",
        "cpws_al_wsxz": "",
        "cpws_al_ts": "05",
        "cpws_al_ts_name": "（刑四庭）",
        "cpws_al_sf": "重庆市",
        "cpws_al_source_id": [
          "0101"
        ],
        "cpws_al_lzgc": "",
        "cpws_al_zdyy": "",
        "cpws_al_jdhg_id": "1234098138822746112",
        "ai_score": 0.0,
        "cpws_al_new_zdxal": ""
      },
      {
        "id": "EPa9WbGwgDKoHDWavGGEsJS5id%2BsRx3Tk1RFI70FWDU%3D",
        "cpws_al_id": "EPa9WbGwgDKoHDWavGGEsJS5id%2BsRx3Tk1RFI70FWDU%3D",
        "cpws_al_type": "02",
        "cpws_al_status": "01",
        "cpws_al_fb_date": "",
        "cpws_al_no": "2024-04-1-139-001",
        "cpws_al_title": "武某信用卡诈骗案",
        "cpws_al_case_sort_id": [
          "01",
          "A01"
        ],
        "cpws_al_case_sort_name": "刑事",
        "cpws_al_sort_name": "信用卡诈骗罪",
        "cpws_al_slfy_name": "山西省太原市中级人民法院",
        "cpws_al_slfy_sf_name": "山西省",
        "cpws_al_zs_date": "2023.06.29",
        "cpws_al_ajzh": "（2023）晋01刑终142号",
        "cpws_al_slcx_name": "二审",
        "cpws_al_cpyz": "　　行为人盗刷他人信用卡过程中，要求套现人员将通过虚构交易方式盗刷的款项转账至其本人账户，是上游犯罪的完成行为，没有改变或者超出上游犯罪的评价范围，不宜重复认定为“自洗钱”行为。上述行为不构成洗钱罪，依法以信用卡诈骗罪论处。",
        "cpws_al_fyjb_id": "",
        "cpws_al_fyjb_name": "",
        "cpws_al_spnf": "",
        "cpws_al_fbnf": "",
        "cpws_al_fulltext": "",
        "cpws_al_jbaq": "",
        "cpws_al_cpjg": "",
        "cpws_al_cply": "",
        "cpws_al_aljz": "",
        "cpws_al_glsy": "",
        "cpws_al_sub_title": "",
        "cpws_al_is_del": "",
        "cpws_al_infos": "2024-04-1-139-001 / 刑事 / 信用卡诈骗罪 / 山西省太原市中级人民法院 / 2023.06.29 / （2023）晋01刑终142号 / 二审 / 入库日期：2024.12.23 / 修改日期：2025.06.26",
        "cpws_al_fbxx": "",
        "cpws_al_sxcpr": "",
        "cpws_al_pdls": "",
        "sort_num": "27678",
        "cpws_al_add_time": "",
        "cpws_al_rk_time": "2024-12-23 13:34:51",
        "cpws_al_update_time": "2025-06-26 10:58:09",
        "cpws_al_wsxz": "",
        "cpws_al_ts": "04",
        "cpws_al_ts_name": "（刑三庭）",
        "cpws_al_sf": "山西省",
        "cpws_al_source_id": [
          "0101"
        ],
        "cpws_al_lzgc": "",
        "cpws_al_zdyy": "",
        "cpws_al_jdhg_id": "1202312418181521408",
        "ai_score": 0.0,
        "cpws_al_new_zdxal": ""
      },
      {
        "id": "RqDiSQgeEU7w0i7d7EuQmLH%2BxqxgzmXhBlkCO8mOBGM%3D",
        "cpws_al_id": "RqDiSQgeEU7w0i7d7EuQmLH%2BxqxgzmXhBlkCO8mOBGM%3D",
        "cpws_al_type": "02",
        "cpws_al_status": "01",
        "cpws_al_fb_date": "",
        "cpws_al_no": "2024-04-1-179-003",
        "cpws_al_title": "赵某健故意伤害案",
        "cpws_al_case_sort_id": [
          "01",
          "A01"
        ],
        "cpws_al_case_sort_name": "刑事",
        "cpws_al_sort_name": "故意伤害罪",
        "cpws_al_slfy_name": "广东省江门市中级人民法院",
        "cpws_al_slfy_sf_name": "广东省",
        "cpws_al_zs_date": "2023.03.20",
        "cpws_al_ajzh": "（2023）粤07刑终76号",
        "cpws_al_slcx_name": "二审",
        "cpws_al_cpyz": "　　    被告人在邻里间轻微矛盾平息后，又对被害人实施故意伤害行为的，不应认定被害人对引发的故意伤害案件具有刑法意义上的过错。<br/>　　",
        "cpws_al_fyjb_id": "",
        "cpws_al_fyjb_name": "",
        "cpws_al_spnf": "",
        "cpws_al_fbnf": "",
        "cpws_al_fulltext": "",
        "cpws_al_jbaq": "",
        "cpws_al_cpjg": "",
        "cpws_al_cply": "",
        "cpws_al_aljz": "",
        "cpws_al_glsy": "",
        "cpws_al_sub_title": "",
        "cpws_al_is_del": "",
        "cpws_al_infos": "2024-04-1-179-003 / 刑事 / 故意伤害罪 / 广东省江门市中级人民法院 / 2023.03.20 / （2023）粤07刑终76号 / 二审 / 入库日期：2024.12.23",
        "cpws_al_fbxx": "",
        "cpws_al_sxcpr": "",
        "cpws_al_pdls": "",
        "sort_num": "27678",
        "cpws_al_add_time": "",
        "cpws_al_rk_time": "2024-12-23 13:34:49",
        "cpws_al_update_time": "",
        "cpws_al_wsxz": "",
        "cpws_al_ts": "04",
        "cpws_al_ts_name": "（刑三庭）",
        "cpws_al_sf": "广东省",
        "cpws_al_source_id": [
          "0101"
        ],
        "cpws_al_lzgc": "",
        "cpws_al_zdyy": "",
        "cpws_al_jdhg_id": "1212061432019951616",
        "ai_score": 0.0,
        "cpws_al_new_zdxal": ""
      },
      {
        "id": "T5bq8IZjrUPmyfNFzP22ucXwNyzrDhW6IaffbbfbhiU%3D",
        "cpws_al_id": "T5bq8IZjrUPmyfNFzP22ucXwNyzrDhW6IaffbbfbhiU%3D",
        "cpws_al_type": "02",
        "cpws_al_status": "01",
        "cpws_al_fb_date": "",
        "cpws_al_no": "2024-02-1-182-002",
        "cpws_al_title": "袁某生强奸、猥亵儿童案",
        "cpws_al_case_sort_id": [
          "01",
          "A01"
        ],
        "cpws_al_case_sort_name": "刑事",
        "cpws_al_sort_name": "强奸罪",
        "cpws_al_slfy_name": "汾阳市人民法院",
        "cpws_al_slfy_sf_name": "山西省",
        "cpws_al_zs_date": "2023.12.30",
        "cpws_al_ajzh": "（2023）晋1182刑初236号",
        "cpws_al_slcx_name": "一审",
        "cpws_al_cpyz": "　　    行为人针对同一幼女多次实施性侵犯罪过程中，在强奸行为之外的时间、空间又实施猥亵行为的，不应认为猥亵行为是强奸行为的一部分，应当以强奸罪和猥亵儿童罪并罚。<br/>　　",
        "cpws_al_fyjb_id": "",
        "cpws_al_fyjb_name": "",
        "cpws_al_spnf": "",
        "cpws_al_fbnf": "",
        "cpws_al_fulltext": "",
        "cpws_al_jbaq": "",
        "cpws_al_cpjg": "",
        "cpws_al_cply": "",
        "cpws_al_aljz": "",
        "cpws_al_glsy": "",
        "cpws_al_sub_title": "",
        "cpws_al_is_del": "",
        "cpws_al_infos": "2024-02-1-182-002 / 刑事 / 强奸罪 / 汾阳市人民法院 / 2023.12.30 / （2023）晋1182刑初236号 / 一审 / 入库日期：2024.12.23",
        "cpws_al_fbxx": "",
        "cpws_al_sxcpr": "",
        "cpws_al_pdls": "",
        "sort_num": "27678",
        "cpws_al_add_time": "",
        "cpws_al_rk_time": "2024-12-23 13:34:49",
        "cpws_al_update_time": "",
        "cpws_al_wsxz": "",
        "cpws_al_ts": "02",
        "cpws_al_ts_name": "（刑一庭）",
        "cpws_al_sf": "山西省",
        "cpws_al_source_id": [
          "0101"
        ],
        "cpws_al_lzgc": "",
        "cpws_al_zdyy": "",
        "cpws_al_jdhg_id": "1209924281606086656",
        "ai_score": 0.0,
        "cpws_al_new_zdxal": ""
      },
      {
        "id": "Ffb44FzlNBRnaVl3t5zLt1cFFqZtegieIQfFd6semts%3D",
        "cpws_al_id": "Ffb44FzlNBRnaVl3t5zLt1cFFqZtegieIQfFd6semts%3D",
        "cpws_al_type": "02",
        "cpws_al_status": "01",
        "cpws_al_fb_date": "",
        "cpws_al_no": "2024-05-1-015-001",
        "cpws_al_title": "林某遵爆炸案",
        "cpws_al_case_sort_id": [
          "01",
          "A01"
        ],
        "cpws_al_case_sort_name": "刑事",
        "cpws_al_sort_name": "爆炸罪",
        "cpws_al_slfy_name": "广东省阳江市中级人民法院",
        "cpws_al_slfy_sf_name": "广东省",
        "cpws_al_zs_date": "2023.10.13",
        "cpws_al_ajzh": "（2023）粤17刑终113号",
        "cpws_al_slcx_name": "二审",
        "cpws_al_cpyz": "　　    爆炸罪和以爆炸方法实施的故意伤害罪，区别主要在于侵害的客体不同。前者所侵害的客体为公共安全，后者所侵害的客体为他人的生命健康安全。行为人以特定人为爆炸对象，但受诸多客观因素的影响，难以将爆炸控制在特定人或物的范围之内，可能造成不特定多数人伤亡或公私财产损失，而其主观上又对危害公共安全的后果持放任态度的，应以爆炸罪论处。<br/>　　",
        "cpws_al_fyjb_id": "",
        "cpws_al_fyjb_name": "",
        "cpws_al_spnf": "",
        "cpws_al_fbnf": "",
        "cpws_al_fulltext": "",
        "cpws_al_jbaq": "",
        "cpws_al_cpjg": "",
        "cpws_al_cply": "",
        "cpws_al_aljz": "",
        "cpws_al_glsy": "",
        "cpws_al_sub_title": "",
        "cpws_al_is_del": "",
        "cpws_al_infos": "2024-05-1-015-001 / 刑事 / 爆炸罪 / 广东省阳江市中级人民法院 / 2023.10.13 / （2023）粤17刑终113号 / 二审 / 入库日期：2024.12.23",
        "cpws_al_fbxx": "",
        "cpws_al_sxcpr": "",
        "cpws_al_pdls": "",
        "sort_num": "27678",
        "cpws_al_add_time": "",
        "cpws_al_rk_time": "2024-12-23 13:34:48",
        "cpws_al_update_time": "",
        "cpws_al_wsxz": "",
        "cpws_al_ts": "05",
        "cpws_al_ts_name": "（刑四庭）",
        "cpws_al_sf": "广东省",
        "cpws_al_source_id": [
          "0101"
        ],
        "cpws_al_lzgc": "",
        "cpws_al_zdyy": "",
        "cpws_al_jdhg_id": "1219972410246176768",
        "ai_score": 0.0,
        "cpws_al_new_zdxal": ""
      },
      {
        "id": "QseZcIZE9dXXLwuG5drqyglMvZ5a%2F8ioIVG%2BU3Or3jU%3D",
        "cpws_al_id": "QseZcIZE9dXXLwuG5drqyglMvZ5a%2F8ioIVG%2BU3Or3jU%3D",
        "cpws_al_type": "02",
        "cpws_al_status": "01",
        "cpws_al_fb_date": "",
        "cpws_al_no": "2024-04-1-179-002",
        "cpws_al_title": "王某民、高某、徐某芬故意伤害案",
        "cpws_al_case_sort_id": [
          "01",
          "A01"
        ],
        "cpws_al_case_sort_name": "刑事",
        "cpws_al_sort_name": "故意伤害罪",
        "cpws_al_slfy_name": "上海市第一中级人民法院",
        "cpws_al_slfy_sf_name": "上海市",
        "cpws_al_zs_date": "2022.09.29",
        "cpws_al_ajzh": "（2022）沪01刑终334号",
        "cpws_al_slcx_name": "二审",
        "cpws_al_cpyz": "　　    “随意殴打他人”型寻衅滋事罪与故意伤害罪的区分，一是看侵犯的客体，前者是复杂客观，主要是侵犯公共秩序，同时侵犯了公民的身体健康权利；二是看客观方面，前者通常在作案对象的选择上具有随意性，后者通常是事出有因，侵犯的对象特定；三是看主观方面，前者主要是基于寻求刺激、逞强耍横等动机，无事生非、借故生非，后者多是因民间矛盾引起，在矛盾激化过程基于情绪失控的因素使用暴力。行为人殴打被害人，如果事出有因，或者此前双方已有矛盾，或者事发时因被害人言语不当等原因引起，不应定性为“随意殴打他人”型寻衅滋事。<br/>　　",
        "cpws_al_fyjb_id": "",
        "cpws_al_fyjb_name": "",
        "cpws_al_spnf": "",
        "cpws_al_fbnf": "",
        "cpws_al_fulltext": "",
        "cpws_al_jbaq": "",
        "cpws_al_cpjg": "",
        "cpws_al_cply": "",
        "cpws_al_aljz": "",
        "cpws_al_glsy": "",
        "cpws_al_sub_title": "",
        "cpws_al_is_del": "",
        "cpws_al_infos": "2024-04-1-179-002 / 刑事 / 故意伤害罪 / 上海市第一中级人民法院 / 2022.09.29 / （2022）沪01刑终334号 / 二审 / 入库日期：2024.12.23",
        "cpws_al_fbxx": "",
        "cpws_al_sxcpr": "",
        "cpws_al_pdls": "",
        "sort_num": "27678",
        "cpws_al_add_time": "",
        "cpws_al_rk_time": "2024-12-23 13:34:45",
        "cpws_al_update_time": "",
        "cpws_al_wsxz": "",
        "cpws_al_ts": "04",
        "cpws_al_ts_name": "（刑三庭）",
        "cpws_al_sf": "上海市",
        "cpws_al_source_id": [
          "0101"
        ],
        "cpws_al_lzgc": "",
        "cpws_al_zdyy": "",
        "cpws_al_jdhg_id": "1197109596519403520",
        "ai_score": 0.0,
        "cpws_al_new_zdxal": ""
      },
      {
        "id": "jnTeHV7KpoClagfrTbUIpWD6oPzNdnMN5TfQafPB6XM%3D",
        "cpws_al_id": "jnTeHV7KpoClagfrTbUIpWD6oPzNdnMN5TfQafPB6XM%3D",
        "cpws_al_type": "02",
        "cpws_al_status": "01",
        "cpws_al_fb_date": "",
        "cpws_al_no": "2024-03-1-254-001",
        "cpws_al_title": "钱某等破坏计算机信息系统案",
        "cpws_al_case_sort_id": [
          "01",
          "A01"
        ],
        "cpws_al_case_sort_name": "刑事",
        "cpws_al_sort_name": "破坏计算机信息系统罪",
        "cpws_al_slfy_name": "安徽省芜湖市中级人民法院",
        "cpws_al_slfy_sf_name": "安徽省",
        "cpws_al_zs_date": "2022.11.03",
        "cpws_al_ajzh": "（2022）皖02刑终170号",
        "cpws_al_slcx_name": "二审",
        "cpws_al_cpyz": "　　     非法获取政府公共服务管理平台账号、密码，非法录入、审批虚假信息，造成该计算机信息系统中存储的数据失真，属于刑法第二百八十六条第二款规定的“对计算机信息系统中存储、处理或者传输的数据和应用程序进行删除、修改、增加的操作”。<br/>　　",
        "cpws_al_fyjb_id": "",
        "cpws_al_fyjb_name": "",
        "cpws_al_spnf": "",
        "cpws_al_fbnf": "",
        "cpws_al_fulltext": "",
        "cpws_al_jbaq": "",
        "cpws_al_cpjg": "",
        "cpws_al_cply": "",
        "cpws_al_aljz": "",
        "cpws_al_glsy": "",
        "cpws_al_sub_title": "",
        "cpws_al_is_del": "",
        "cpws_al_infos": "2024-03-1-254-001 / 刑事 / 破坏计算机信息系统罪 / 安徽省芜湖市中级人民法院 / 2022.11.03 / （2022）皖02刑终170号 / 二审 / 入库日期：2024.12.23",
        "cpws_al_fbxx": "",
        "cpws_al_sxcpr": "",
        "cpws_al_pdls": "",
        "sort_num": "27678",
        "cpws_al_add_time": "",
        "cpws_al_rk_time": "2024-12-23 13:34:45",
        "cpws_al_update_time": "",
        "cpws_al_wsxz": "",
        "cpws_al_ts": "03",
        "cpws_al_ts_name": "（刑二庭）",
        "cpws_al_sf": "安徽省",
        "cpws_al_source_id": [
          "0101"
        ],
        "cpws_al_lzgc": "",
        "cpws_al_zdyy": "",
        "cpws_al_jdhg_id": "1197852841817944064",
        "ai_score": 0.0,
        "cpws_al_new_zdxal": ""
      },
      {
        "id": "p0hZeaeSdGbISrUGspUn1NTXsLvinFHxYfEaPWLC3%2FA%3D",
        "cpws_al_id": "p0hZeaeSdGbISrUGspUn1NTXsLvinFHxYfEaPWLC3%2FA%3D",
        "cpws_al_type": "02",
        "cpws_al_status": "01",
        "cpws_al_fb_date": "",
        "cpws_al_no": "2024-04-1-207-001",
        "cpws_al_title": "毛某斌侵犯公民个人信息案",
        "cpws_al_case_sort_id": [
          "01",
          "A01"
        ],
        "cpws_al_case_sort_name": "刑事",
        "cpws_al_sort_name": "侵犯公民个人信息罪",
        "cpws_al_slfy_name": "广东省清远市中级人民法院",
        "cpws_al_slfy_sf_name": "广东省",
        "cpws_al_zs_date": "2024.01.30",
        "cpws_al_ajzh": "（2023）粤18刑终331号",
        "cpws_al_slcx_name": "二审",
        "cpws_al_cpyz": "　　1.车辆轨迹、定位信息等可以直接定位特定自然人具体坐标的信息，应当认定为《最高人民法院、最高人民检察院关于办理侵犯公民个人信息刑事案件适用法律若干问题的解释》（法释〔2017〕10号）第五条规定的“行踪轨迹信息”。<br/>　　2.行踪轨迹信息等因涉及人身财产安全，系敏感公民个人信息，入罪标准较低，应当逐一认定，确保定罪量刑准确。对于被害人在某地点处于静止状态下的重复定位信息，应当计算为一条信息。<br/>　　",
        "cpws_al_fyjb_id": "",
        "cpws_al_fyjb_name": "",
        "cpws_al_spnf": "",
        "cpws_al_fbnf": "",
        "cpws_al_fulltext": "",
        "cpws_al_jbaq": "",
        "cpws_al_cpjg": "",
        "cpws_al_cply": "",
        "cpws_al_aljz": "",
        "cpws_al_glsy": "",
        "cpws_al_sub_title": "",
        "cpws_al_is_del": "",
        "cpws_al_infos": "2024-04-1-207-001 / 刑事 / 侵犯公民个人信息罪 / 广东省清远市中级人民法院 / 2024.01.30 / （2023）粤18刑终331号 / 二审 / 入库日期：2024.12.23",
        "cpws_al_fbxx": "",
        "cpws_al_sxcpr": "",
        "cpws_al_pdls": "",
        "sort_num": "27678",
        "cpws_al_add_time": "",
        "cpws_al_rk_time": "2024-12-23 13:34:41",
        "cpws_al_update_time": "",
        "cpws_al_wsxz": "",
        "cpws_al_ts": "04",
        "cpws_al_ts_name": "（刑三庭）",
        "cpws_al_sf": "广东省",
        "cpws_al_source_id": [
          "0101"
        ],
        "cpws_al_lzgc": "",
        "cpws_al_zdyy": "",
        "cpws_al_jdhg_id": "1230110494380007424",
        "ai_score": 0.0,
        "cpws_al_new_zdxal": ""
      },
      {
        "id": "Ozh%2FOL4t0Z%2FMO%2FZI6%2Fa1kYc6KZu0TROGC9N023D1%2FCw%3D",
        "cpws_al_id": "Ozh%2FOL4t0Z%2FMO%2FZI6%2Fa1kYc6KZu0TROGC9N023D1%2FCw%3D",
        "cpws_al_type": "02",
        "cpws_al_status": "01",
        "cpws_al_fb_date": "",
        "cpws_al_no": "2024-02-1-185-002",
        "cpws_al_title": "高某水、刘某一猥亵儿童、引诱未成年人聚众淫乱案",
        "cpws_al_case_sort_id": [
          "01",
          "A01"
        ],
        "cpws_al_case_sort_name": "刑事",
        "cpws_al_sort_name": "猥亵儿童罪",
        "cpws_al_slfy_name": "北京市石景山区人民法院",
        "cpws_al_slfy_sf_name": "北京市",
        "cpws_al_zs_date": "2022.05.10",
        "cpws_al_ajzh": "（2021）京0107刑初466号",
        "cpws_al_slcx_name": "一审",
        "cpws_al_cpyz": "　　    被告人介绍他人对不满十四周岁的男童实施猥亵，或者引诱男童对被告人本人实施肛交的，均构成猥亵儿童罪。<br/>　　",
        "cpws_al_fyjb_id": "",
        "cpws_al_fyjb_name": "",
        "cpws_al_spnf": "",
        "cpws_al_fbnf": "",
        "cpws_al_fulltext": "",
        "cpws_al_jbaq": "",
        "cpws_al_cpjg": "",
        "cpws_al_cply": "",
        "cpws_al_aljz": "",
        "cpws_al_glsy": "",
        "cpws_al_sub_title": "",
        "cpws_al_is_del": "",
        "cpws_al_infos": "2024-02-1-185-002 / 刑事 / 猥亵儿童罪 / 北京市石景山区人民法院 / 2022.05.10 / （2021）京0107刑初466号 / 一审 / 入库日期：2024.12.23",
        "cpws_al_fbxx": "",
        "cpws_al_sxcpr": "",
        "cpws_al_pdls": "",
        "sort_num": "27678",
        "cpws_al_add_time": "",
        "cpws_al_rk_time": "2024-12-23 13:34:40",
        "cpws_al_update_time": "",
        "cpws_al_wsxz": "",
        "cpws_al_ts": "02",
        "cpws_al_ts_name": "（刑一庭）",
        "cpws_al_sf": "北京市",
        "cpws_al_source_id": [
          "0101"
        ],
        "cpws_al_lzgc": "",
        "cpws_al_zdyy": "",
        "cpws_al_jdhg_id": "1195387812308856832",
        "ai_score": 0.0,
        "cpws_al_new_zdxal": ""
      },
      {
        "id": "HZFLzMwMAuEuuek0kSfz2XozNJoVq9h7Cq0iW3mBDBc%3D",
        "cpws_al_id": "HZFLzMwMAuEuuek0kSfz2XozNJoVq9h7Cq0iW3mBDBc%3D",
        "cpws_al_type": "02",
        "cpws_al_status": "01",
        "cpws_al_fb_date": "",
        "cpws_al_no": "2024-06-1-178-004",
        "cpws_al_title": "邱某潮过失致人死亡案",
        "cpws_al_case_sort_id": [
          "01",
          "A01"
        ],
        "cpws_al_case_sort_name": "刑事",
        "cpws_al_sort_name": "过失致人死亡罪",
        "cpws_al_slfy_name": "上海市徐汇区人民法院",
        "cpws_al_slfy_sf_name": "上海市",
        "cpws_al_zs_date": "2020.04.23",
        "cpws_al_ajzh": "（2019）沪0104刑初1298号",
        "cpws_al_slcx_name": "一审",
        "cpws_al_cpyz": "　　    行为人实施危险程度较低的轻微暴力行为，未直接造成被害人伤害后果，而是因被害人自身疾病发作等因素导致被害人死亡的，应当综合考量行为人的主观罪过、行为的暴力程度及行为、特殊体质与死亡结果之间的因果关系等情节，依法作出准确定性。尽管所涉轻微暴力不会造成伤害后果，但可能诱发被害人自身疾病发作致死，且行为人对此有过失的，以过失致人死亡罪论处。<br/>　　",
        "cpws_al_fyjb_id": "",
        "cpws_al_fyjb_name": "",
        "cpws_al_spnf": "",
        "cpws_al_fbnf": "",
        "cpws_al_fulltext": "",
        "cpws_al_jbaq": "",
        "cpws_al_cpjg": "",
        "cpws_al_cply": "",
        "cpws_al_aljz": "",
        "cpws_al_glsy": "",
        "cpws_al_sub_title": "",
        "cpws_al_is_del": "",
        "cpws_al_infos": "2024-06-1-178-004 / 刑事 / 过失致人死亡罪 / 上海市徐汇区人民法院 / 2020.04.23 / （2019）沪0104刑初1298号 / 一审 / 入库日期：2024.12.23",
        "cpws_al_fbxx": "",
        "cpws_al_sxcpr": "",
        "cpws_al_pdls": "",
        "sort_num": "27678",
        "cpws_al_add_time": "",
        "cpws_al_rk_time": "2024-12-23 13:24:46",
        "cpws_al_update_time": "",
        "cpws_al_wsxz": "",
        "cpws_al_ts": "06",
        "cpws_al_ts_name": "（刑五庭）",
        "cpws_al_sf": "上海市",
        "cpws_al_source_id": [
          "0101"
        ],
        "cpws_al_lzgc": "",
        "cpws_al_zdyy": "",
        "cpws_al_jdhg_id": "1195374366058098688",
        "ai_score": 0.0,
        "cpws_al_new_zdxal": ""
      },
      {
        "id": "uJcZr5qp3GyUwyadDspo2Eozv09CUUOuWzwIqjXLXs4%3D",
        "cpws_al_id": "uJcZr5qp3GyUwyadDspo2Eozv09CUUOuWzwIqjXLXs4%3D",
        "cpws_al_type": "02",
        "cpws_al_status": "01",
        "cpws_al_fb_date": "",
        "cpws_al_no": "2024-04-1-222-010",
        "cpws_al_title": "王某等诈骗案",
        "cpws_al_case_sort_id": [
          "01",
          "A01"
        ],
        "cpws_al_case_sort_name": "刑事",
        "cpws_al_sort_name": "诈骗罪",
        "cpws_al_slfy_name": "山东省威海市中级人民法院",
        "cpws_al_slfy_sf_name": "山东省",
        "cpws_al_zs_date": "2022.05.06",
        "cpws_al_ajzh": "（2022）鲁10刑终34号",
        "cpws_al_slcx_name": "二审",
        "cpws_al_cpyz": "　　电信网络诈骗案件中，犯罪分子往往广泛撒网，通过微信、QQ、抖音等网络平台实施诈骗的引流任务，再由电信网络诈骗团伙对被害人通过各种方式实施诈骗。对于上述“吸粉引流”行为的定性，应当结合行为人对上游犯罪团伙实施诈骗行为的明知程度、行为人与上游犯罪联系的紧密度和稳定度等因素进行综合判断。如“吸粉引流”团伙与上游诈骗分子联系密切，“引流名单”和“话术”均由上家提供，事先通谋或者形成长期稳定配合关系的，应当依照刑法第二百六十六条的规定，以诈骗罪共犯论处。",
        "cpws_al_fyjb_id": "",
        "cpws_al_fyjb_name": "",
        "cpws_al_spnf": "",
        "cpws_al_fbnf": "",
        "cpws_al_fulltext": "",
        "cpws_al_jbaq": "",
        "cpws_al_cpjg": "",
        "cpws_al_cply": "",
        "cpws_al_aljz": "",
        "cpws_al_glsy": "",
        "cpws_al_sub_title": "",
        "cpws_al_is_del": "",
        "cpws_al_infos": "2024-04-1-222-010 / 刑事 / 诈骗罪 / 山东省威海市中级人民法院 / 2022.05.06 / （2022）鲁10刑终34号 / 二审 / 入库日期：2024.12.23 / 修改日期：2025.06.06",
        "cpws_al_fbxx": "",
        "cpws_al_sxcpr": "",
        "cpws_al_pdls": "",
        "sort_num": "27678",
        "cpws_al_add_time": "",
        "cpws_al_rk_time": "2024-12-23 13:24:45",
        "cpws_al_update_time": "2025-06-06 15:03:07",
        "cpws_al_wsxz": "",
        "cpws_al_ts": "04",
        "cpws_al_ts_name": "（刑三庭）",
        "cpws_al_sf": "山东省",
        "cpws_al_source_id": [
          "0101"
        ],
        "cpws_al_lzgc": "",
        "cpws_al_zdyy": "",
        "cpws_al_jdhg_id": "1196412664692092928",
        "ai_score": 0.0,
        "cpws_al_new_zdxal": ""
      },
      {
        "id": "J1CHdLq1HE04q%2BKlYjsjUkg6nti%2FNpPx3mBISrb%2Bn9I%3D",
        "cpws_al_id": "J1CHdLq1HE04q%2BKlYjsjUkg6nti%2FNpPx3mBISrb%2Bn9I%3D",
        "cpws_al_type": "02",
        "cpws_al_status": "01",
        "cpws_al_fb_date": "",
        "cpws_al_no": "2024-05-1-220-003",
        "cpws_al_title": "李某、宋某增抢劫、盗窃案",
        "cpws_al_case_sort_id": [
          "01",
          "A01"
        ],
        "cpws_al_case_sort_name": "刑事",
        "cpws_al_sort_name": "抢劫罪",
        "cpws_al_slfy_name": "柳州市柳北区人民法院",
        "cpws_al_slfy_sf_name": "广西壮族自治区",
        "cpws_al_zs_date": "2022.04.13",
        "cpws_al_ajzh": "（2022）桂0205刑初75号",
        "cpws_al_slcx_name": "一审",
        "cpws_al_cpyz": "　　携带凶器连续盗窃后暴力拒捕，若第一次盗窃行为已呈终局状态、独立构成犯罪，且与后续实施的暴力行为联系不紧密，即不符合转化型抢劫的“当场性”特征，应当以盗窃罪与抢劫罪数罪并罚。<br/>　　",
        "cpws_al_fyjb_id": "",
        "cpws_al_fyjb_name": "",
        "cpws_al_spnf": "",
        "cpws_al_fbnf": "",
        "cpws_al_fulltext": "",
        "cpws_al_jbaq": "",
        "cpws_al_cpjg": "",
        "cpws_al_cply": "",
        "cpws_al_aljz": "",
        "cpws_al_glsy": "",
        "cpws_al_sub_title": "",
        "cpws_al_is_del": "",
        "cpws_al_infos": "2024-05-1-220-003 / 刑事 / 抢劫罪 / 柳州市柳北区人民法院 / 2022.04.13 / （2022）桂0205刑初75号 / 一审 / 入库日期：2024.12.23",
        "cpws_al_fbxx": "",
        "cpws_al_sxcpr": "",
        "cpws_al_pdls": "",
        "sort_num": "27678",
        "cpws_al_add_time": "",
        "cpws_al_rk_time": "2024-12-23 13:24:43",
        "cpws_al_update_time": "",
        "cpws_al_wsxz": "",
        "cpws_al_ts": "05",
        "cpws_al_ts_name": "（刑四庭）",
        "cpws_al_sf": "广西壮族自治区",
        "cpws_al_source_id": [
          "0101"
        ],
        "cpws_al_lzgc": "",
        "cpws_al_zdyy": "",
        "cpws_al_jdhg_id": "1194311393331916800",
        "ai_score": 0.0,
        "cpws_al_new_zdxal": ""
      },
      {
        "id": "i6EkzM0ST3A%2BKasXq0MLJLPREN%2ForocbEDwzz51rwPU%3D",
        "cpws_al_id": "i6EkzM0ST3A%2BKasXq0MLJLPREN%2ForocbEDwzz51rwPU%3D",
        "cpws_al_type": "02",
        "cpws_al_status": "01",
        "cpws_al_fb_date": "",
        "cpws_al_no": "2024-03-1-404-017",
        "cpws_al_title": "马某选受贿案",
        "cpws_al_case_sort_id": [
          "01",
          "A01"
        ],
        "cpws_al_case_sort_name": "刑事",
        "cpws_al_sort_name": "受贿罪",
        "cpws_al_slfy_name": "四川省成都市中级人民法院",
        "cpws_al_slfy_sf_name": "四川省",
        "cpws_al_zs_date": "2018.12.11",
        "cpws_al_ajzh": "（2016）川01刑初108号",
        "cpws_al_slcx_name": "一审",
        "cpws_al_cpyz": "　　    被告人在案发前向廉政账户上交款项是否应从受贿数额中扣除，应结合上交时间距离收受时间长短、上交具体原因、上交款项占受贿总额比例等情况进行综合判断。收受后长时期未上交，案发前为了掩饰犯罪仅上交极少部分的受贿款，可不再从受贿数额中扣除。无证据证明上交款项属于其他违法违纪所得的情况，上交部分应从责令退赃数额中扣减。<br/>　　",
        "cpws_al_fyjb_id": "",
        "cpws_al_fyjb_name": "",
        "cpws_al_spnf": "",
        "cpws_al_fbnf": "",
        "cpws_al_fulltext": "",
        "cpws_al_jbaq": "",
        "cpws_al_cpjg": "",
        "cpws_al_cply": "",
        "cpws_al_aljz": "",
        "cpws_al_glsy": "",
        "cpws_al_sub_title": "",
        "cpws_al_is_del": "",
        "cpws_al_infos": "2024-03-1-404-017 / 刑事 / 受贿罪 / 四川省成都市中级人民法院 / 2018.12.11 / （2016）川01刑初108号 / 一审 / 入库日期：2024.12.23",
        "cpws_al_fbxx": "",
        "cpws_al_sxcpr": "",
        "cpws_al_pdls": "",
        "sort_num": "27678",
        "cpws_al_add_time": "",
        "cpws_al_rk_time": "2024-12-23 13:24:41",
        "cpws_al_update_time": "",
        "cpws_al_wsxz": "",
        "cpws_al_ts": "03",
        "cpws_al_ts_name": "（刑二庭）",
        "cpws_al_sf": "四川省",
        "cpws_al_source_id": [
          "0101"
        ],
        "cpws_al_lzgc": "",
        "cpws_al_zdyy": "",
        "cpws_al_jdhg_id": "1270303789324181504",
        "ai_score": 0.0,
        "cpws_al_new_zdxal": ""
      },
      {
        "id": "ik95HGFAxI3xB67cg2ww51PrN9MGww03wHBV3xAI%2FbQ%3D",
        "cpws_al_id": "ik95HGFAxI3xB67cg2ww51PrN9MGww03wHBV3xAI%2FbQ%3D",
        "cpws_al_type": "02",
        "cpws_al_status": "01",
        "cpws_al_fb_date": "",
        "cpws_al_no": "2024-06-1-195-001",
        "cpws_al_title": "先某川非法侵入住宅、盗窃案",
        "cpws_al_case_sort_id": [
          "01",
          "A01"
        ],
        "cpws_al_case_sort_name": "刑事",
        "cpws_al_sort_name": "非法侵入住宅罪",
        "cpws_al_slfy_name": "合江县人民法院",
        "cpws_al_slfy_sf_name": "四川省",
        "cpws_al_zs_date": "2023.10.31",
        "cpws_al_ajzh": "（2023）川0522刑初212号",
        "cpws_al_slcx_name": "一审",
        "cpws_al_cpyz": "　　   行为人未经住宅主人同意，非法侵入他人住宅居住且长达数日的，其行为构成非法侵入住宅罪。非法居住期间临时起意窃取住宅内价值较大以上财物的，同时构成盗窃罪。该盗窃行为与非法侵入他人住宅的行为相对独立，应当以非法侵入住宅罪和盗窃罪数罪并罚。 <br/>　　",
        "cpws_al_fyjb_id": "",
        "cpws_al_fyjb_name": "",
        "cpws_al_spnf": "",
        "cpws_al_fbnf": "",
        "cpws_al_fulltext": "",
        "cpws_al_jbaq": "",
        "cpws_al_cpjg": "",
        "cpws_al_cply": "",
        "cpws_al_aljz": "",
        "cpws_al_glsy": "",
        "cpws_al_sub_title": "",
        "cpws_al_is_del": "",
        "cpws_al_infos": "2024-06-1-195-001 / 刑事 / 非法侵入住宅罪 / 合江县人民法院 / 2023.10.31 / （2023）川0522刑初212号 / 一审 / 入库日期：2024.12.23",
        "cpws_al_fbxx": "",
        "cpws_al_sxcpr": "",
        "cpws_al_pdls": "",
        "sort_num": "27678",
        "cpws_al_add_time": "",
        "cpws_al_rk_time": "2024-12-23 13:24:36",
        "cpws_al_update_time": "",
        "cpws_al_wsxz": "",
        "cpws_al_ts": "06",
        "cpws_al_ts_name": "（刑五庭）",
        "cpws_al_sf": "四川省",
        "cpws_al_source_id": [
          "0101"
        ],
        "cpws_al_lzgc": "",
        "cpws_al_zdyy": "",
        "cpws_al_jdhg_id": "1189535381729574912",
        "ai_score": 0.0,
        "cpws_al_new_zdxal": ""
      },
      {
        "id": "qj357KV1E55m7f%2B6OJwmu3dCYqpRpdLfWYZj9qrKVDQ%3D",
        "cpws_al_id": "qj357KV1E55m7f%2B6OJwmu3dCYqpRpdLfWYZj9qrKVDQ%3D",
        "cpws_al_type": "02",
        "cpws_al_status": "01",
        "cpws_al_fb_date": "",
        "cpws_al_no": "2024-03-1-169-005",
        "cpws_al_title": "李某、葛某梦非法经营罪",
        "cpws_al_case_sort_id": [
          "01",
          "A01"
        ],
        "cpws_al_case_sort_name": "刑事",
        "cpws_al_sort_name": "非法经营罪",
        "cpws_al_slfy_name": "苍溪县人民法院",
        "cpws_al_slfy_sf_name": "四川省",
        "cpws_al_zs_date": "2023.08.11",
        "cpws_al_ajzh": "（2023）川0824刑初107号",
        "cpws_al_slcx_name": "一审",
        "cpws_al_cpyz": "　　    冒充客服、虚构相关网站工作人员的身份，接受他人委托，在相关网站上发布帖文、推广，采用操控软件的方式，向他人有偿提供发布虚假评论、制造虚假浏览量等服务，获取利益的，属于刑法第二百二十五条规定的非法经营罪。<br/>　　",
        "cpws_al_fyjb_id": "",
        "cpws_al_fyjb_name": "",
        "cpws_al_spnf": "",
        "cpws_al_fbnf": "",
        "cpws_al_fulltext": "",
        "cpws_al_jbaq": "",
        "cpws_al_cpjg": "",
        "cpws_al_cply": "",
        "cpws_al_aljz": "",
        "cpws_al_glsy": "",
        "cpws_al_sub_title": "",
        "cpws_al_is_del": "",
        "cpws_al_infos": "2024-03-1-169-005 / 刑事 / 非法经营罪 / 苍溪县人民法院 / 2023.08.11 / （2023）川0824刑初107号 / 一审 / 入库日期：2024.12.23",
        "cpws_al_fbxx": "",
        "cpws_al_sxcpr": "",
        "cpws_al_pdls": "",
        "sort_num": "27678",
        "cpws_al_add_time": "",
        "cpws_al_rk_time": "2024-12-23 13:04:30",
        "cpws_al_update_time": "",
        "cpws_al_wsxz": "",
        "cpws_al_ts": "03",
        "cpws_al_ts_name": "（刑二庭）",
        "cpws_al_sf": "四川省",
        "cpws_al_source_id": [
          "0101"
        ],
        "cpws_al_lzgc": "",
        "cpws_al_zdyy": "",
        "cpws_al_jdhg_id": "1187433318937788416",
        "ai_score": 0.0,
        "cpws_al_new_zdxal": ""
      },
      {
        "id": "4pYgjioQ6zzpb5qbs6MIpikCjX%2FNp0BlS83QmyyPhMk%3D",
        "cpws_al_id": "4pYgjioQ6zzpb5qbs6MIpikCjX%2FNp0BlS83QmyyPhMk%3D",
        "cpws_al_type": "02",
        "cpws_al_status": "01",
        "cpws_al_fb_date": "",
        "cpws_al_no": "2024-05-1-301-003",
        "cpws_al_title": "曾某明拒不执行判决、裁定案",
        "cpws_al_case_sort_id": [
          "01",
          "A01"
        ],
        "cpws_al_case_sort_name": "刑事",
        "cpws_al_sort_name": "拒不执行判决、裁定罪",
        "cpws_al_slfy_name": "峡江县人民法院",
        "cpws_al_slfy_sf_name": "江西省",
        "cpws_al_zs_date": "2021.10.09",
        "cpws_al_ajzh": "（2021）赣0823刑初79号",
        "cpws_al_slcx_name": "一审",
        "cpws_al_cpyz": "　　    被执行人有能力履行人民法院生效判决确定的财产给付义务，却以隐瞒、转移经营收入的方式拒不履行，应认定为有能力执行而不执行，情节严重的情形，应当以拒不执行判决裁定罪追究其刑事责任。被执行人在刑事案件审理过程中履行执行义务的，依法酌情对被执行人予以从轻或者免除处罚。<br/>　　",
        "cpws_al_fyjb_id": "",
        "cpws_al_fyjb_name": "",
        "cpws_al_spnf": "",
        "cpws_al_fbnf": "",
        "cpws_al_fulltext": "",
        "cpws_al_jbaq": "",
        "cpws_al_cpjg": "",
        "cpws_al_cply": "",
        "cpws_al_aljz": "",
        "cpws_al_glsy": "",
        "cpws_al_sub_title": "",
        "cpws_al_is_del": "",
        "cpws_al_infos": "2024-05-1-301-003 / 刑事 / 拒不执行判决、裁定罪 / 峡江县人民法院 / 2021.10.09 / （2021）赣0823刑初79号 / 一审 / 入库日期：2024.12.23",
        "cpws_al_fbxx": "",
        "cpws_al_sxcpr": "",
        "cpws_al_pdls": "",
        "sort_num": "27678",
        "cpws_al_add_time": "",
        "cpws_al_rk_time": "2024-12-23 13:04:29",
        "cpws_al_update_time": "",
        "cpws_al_wsxz": "",
        "cpws_al_ts": "05",
        "cpws_al_ts_name": "（刑四庭）",
        "cpws_al_sf": "江西省",
        "cpws_al_source_id": [
          "0101"
        ],
        "cpws_al_lzgc": "",
        "cpws_al_zdyy": "",
        "cpws_al_jdhg_id": "1186269779896303616",
        "ai_score": 0.0,
        "cpws_al_new_zdxal": ""
      },
      {
        "id": "Y4QM5K9IEg%2BOoGovOKuspHlurDAEJDLIfIsPz32x%2FqQ%3D",
        "cpws_al_id": "Y4QM5K9IEg%2BOoGovOKuspHlurDAEJDLIfIsPz32x%2FqQ%3D",
        "cpws_al_type": "02",
        "cpws_al_status": "01",
        "cpws_al_fb_date": "",
        "cpws_al_no": "2024-03-1-070-001",
        "cpws_al_title": "周某源、温某妨害药品管理案",
        "cpws_al_case_sort_id": [
          "01",
          "A01"
        ],
        "cpws_al_case_sort_name": "刑事",
        "cpws_al_sort_name": "妨害药品管理罪",
        "cpws_al_slfy_name": "长兴县人民法院",
        "cpws_al_slfy_sf_name": "浙江省",
        "cpws_al_zs_date": "2023.03.31",
        "cpws_al_ajzh": "（2022）浙0522刑初259号",
        "cpws_al_slcx_name": "一审",
        "cpws_al_cpyz": "　　    被告人私自生产、销售自行研制的中药制剂，经认定属于中成药范畴，未冒充其他药品的，不属于“以非药品冒充药品”“以他种药品冒充此种药品”的假药情形；自行研制中药制剂没有固定、对应含量的国家标准，也不属于“药品成份的含量不符合国家药品标准”的劣药情形。被告人违反药品管理法规，在未取得药品相关批准证明文件情况下生产、销售药品，足以严重危害人体健康的，应当以妨害药品管理罪定罪处罚。<br/>　　",
        "cpws_al_fyjb_id": "",
        "cpws_al_fyjb_name": "",
        "cpws_al_spnf": "",
        "cpws_al_fbnf": "",
        "cpws_al_fulltext": "",
        "cpws_al_jbaq": "",
        "cpws_al_cpjg": "",
        "cpws_al_cply": "",
        "cpws_al_aljz": "",
        "cpws_al_glsy": "",
        "cpws_al_sub_title": "",
        "cpws_al_is_del": "",
        "cpws_al_infos": "2024-03-1-070-001 / 刑事 / 妨害药品管理罪 / 长兴县人民法院 / 2023.03.31 / （2022）浙0522刑初259号 / 一审 / 入库日期：2024.12.23",
        "cpws_al_fbxx": "",
        "cpws_al_sxcpr": "",
        "cpws_al_pdls": "",
        "sort_num": "27678",
        "cpws_al_add_time": "",
        "cpws_al_rk_time": "2024-12-23 09:55:18",
        "cpws_al_update_time": "",
        "cpws_al_wsxz": "",
        "cpws_al_ts": "03",
        "cpws_al_ts_name": "（刑二庭）",
        "cpws_al_sf": "浙江省",
        "cpws_al_source_id": [
          "0101"
        ],
        "cpws_al_lzgc": "",
        "cpws_al_zdyy": "",
        "cpws_al_jdhg_id": "1184902880818102272",
        "ai_score": 0.0,
        "cpws_al_new_zdxal": ""
      },
      {
        "id": "HVzBkSDhUbm1wvlhxp4DfOr17%2BbMbtPI%2B2b743IIZBs%3D",
        "cpws_al_id": "HVzBkSDhUbm1wvlhxp4DfOr17%2BbMbtPI%2B2b743IIZBs%3D",
        "cpws_al_type": "02",
        "cpws_al_status": "01",
        "cpws_al_fb_date": "",
        "cpws_al_no": "2024-18-1-301-002",
        "cpws_al_title": "何某拒不执行判决、裁定案",
        "cpws_al_case_sort_id": [
          "01",
          "A01"
        ],
        "cpws_al_case_sort_name": "刑事",
        "cpws_al_sort_name": "拒不执行判决、裁定罪",
        "cpws_al_slfy_name": "射洪市人民法院",
        "cpws_al_slfy_sf_name": "四川省",
        "cpws_al_zs_date": "2023.04.14",
        "cpws_al_ajzh": "（2023）0981刑初47号",
        "cpws_al_slcx_name": "一审",
        "cpws_al_cpyz": "　　<br/>　　1.负有执行义务的人有能力执行，但拒绝报告财产情况，经采取拘留等强制措施后仍拒不执行的，应当认定为全国人民代表大会常务委员会关于刑法第三百一十三条的解释中规定的“其他有能力执行而拒不执行，情节严重的情形”。认定被执行人是否拒绝报告财产情况，应当结合其履行财产报告制度的情况、执行过程中的搜查情况等因素进行综合判断。<br/>　　<br/>　　2.交纳保证金后被取保候审，如在取保候审期间违反刑事诉讼法第七十一条相关规定的，依法没收部分或者全部保证金。<br/>　　",
        "cpws_al_fyjb_id": "",
        "cpws_al_fyjb_name": "",
        "cpws_al_spnf": "",
        "cpws_al_fbnf": "",
        "cpws_al_fulltext": "",
        "cpws_al_jbaq": "",
        "cpws_al_cpjg": "",
        "cpws_al_cply": "",
        "cpws_al_aljz": "",
        "cpws_al_glsy": "",
        "cpws_al_sub_title": "",
        "cpws_al_is_del": "",
        "cpws_al_infos": "2024-18-1-301-002 / 刑事 / 拒不执行判决、裁定罪 / 射洪市人民法院 / 2023.04.14 / （2023）0981刑初47号 / 一审 / 入库日期：2024.12.23",
        "cpws_al_fbxx": "",
        "cpws_al_sxcpr": "",
        "cpws_al_pdls": "",
        "sort_num": "27678",
        "cpws_al_add_time": "",
        "cpws_al_rk_time": "2024-12-23 09:55:17",
        "cpws_al_update_time": "",
        "cpws_al_wsxz": "",
        "cpws_al_ts": "18",
        "cpws_al_ts_name": "（研究室）",
        "cpws_al_sf": "四川省",
        "cpws_al_source_id": [
          "0101"
        ],
        "cpws_al_lzgc": "",
        "cpws_al_zdyy": "",
        "cpws_al_jdhg_id": "1287729540252049408",
        "ai_score": 0.0,
        "cpws_al_new_zdxal": ""
      },
      {
        "id": "NDtQ70EV5zxgEos7h8su9WZGA37rmF0Z9evNY1uVOkw%3D",
        "cpws_al_id": "NDtQ70EV5zxgEos7h8su9WZGA37rmF0Z9evNY1uVOkw%3D",
        "cpws_al_type": "02",
        "cpws_al_status": "01",
        "cpws_al_fb_date": "",
        "cpws_al_no": "2024-03-1-164-001",
        "cpws_al_title": "李某等损害商业信誉、商品声誉案",
        "cpws_al_case_sort_id": [
          "01",
          "A01"
        ],
        "cpws_al_case_sort_name": "刑事",
        "cpws_al_sort_name": "损害商业信誉、商品声誉罪",
        "cpws_al_slfy_name": "青岛市市南区人民法院",
        "cpws_al_slfy_sf_name": "山东省",
        "cpws_al_zs_date": "2024.01.31",
        "cpws_al_ajzh": "（2023）鲁0202刑初365号",
        "cpws_al_slcx_name": "一审",
        "cpws_al_cpyz": "　　行为人捏造并散布虚假事实，损害他人的商业信誉、商品声誉，导致商品退货等，给他人造成重大损失的，依照刑法第二百二十一条的规定，以损害商业信誉、商品声誉罪论处。对此，《最高人民检察院、公安部关于公安机关管辖的刑事案件立案追诉标准的规定（二）》（公通字〔2022〕12号）第六十六条规定：“捏造并散布虚伪事实，损害他人的商业信誉、商品声誉，涉嫌下列情形之一的，应予立案追诉：（一）给他人造成直接经济损失数额在五十万元以上的……”在审判实践中，可以参照适用上述规定，结合案件具体情况和本地实际，准确判断是否属于“给他人造成重大损失”的情形。此外，所涉行为造成被害人单位同类商品的销售态势低于行业平均增长水平、商品零售量和零售额低于市场预期、公司股价波动幅度与同期上证指数相比呈下行态势等危害后果的，可以作为量刑情节予以综合考量认定。<br/>　　",
        "cpws_al_fyjb_id": "",
        "cpws_al_fyjb_name": "",
        "cpws_al_spnf": "",
        "cpws_al_fbnf": "",
        "cpws_al_fulltext": "",
        "cpws_al_jbaq": "",
        "cpws_al_cpjg": "",
        "cpws_al_cply": "",
        "cpws_al_aljz": "",
        "cpws_al_glsy": "",
        "cpws_al_sub_title": "",
        "cpws_al_is_del": "",
        "cpws_al_infos": "2024-03-1-164-001 / 刑事 / 损害商业信誉、商品声誉罪 / 青岛市市南区人民法院 / 2024.01.31 / （2023）鲁0202刑初365号 / 一审 / 入库日期：2024.12.23",
        "cpws_al_fbxx": "",
        "cpws_al_sxcpr": "",
        "cpws_al_pdls": "",
        "sort_num": "27678",
        "cpws_al_add_time": "",
        "cpws_al_rk_time": "2024-12-23 09:24:22",
        "cpws_al_update_time": "",
        "cpws_al_wsxz": "",
        "cpws_al_ts": "03",
        "cpws_al_ts_name": "（刑二庭）",
        "cpws_al_sf": "山东省",
        "cpws_al_source_id": [
          "0101"
        ],
        "cpws_al_lzgc": "",
        "cpws_al_zdyy": "",
        "cpws_al_jdhg_id": "1304107433760661504",
        "ai_score": 0.0,
        "cpws_al_new_zdxal": ""
      },
      {
        "id": "0f%2FMyv8Xh8RPBiV6bmy5cqyR1c9KnIoAZOzH%2BEld6Tk%3D",
        "cpws_al_id": "0f%2FMyv8Xh8RPBiV6bmy5cqyR1c9KnIoAZOzH%2BEld6Tk%3D",
        "cpws_al_type": "02",
        "cpws_al_status": "01",
        "cpws_al_fb_date": "",
        "cpws_al_no": "2024-03-1-248-003",
        "cpws_al_title": "陈某东组织考试作弊案",
        "cpws_al_case_sort_id": [
          "01",
          "A01"
        ],
        "cpws_al_case_sort_name": "刑事",
        "cpws_al_sort_name": "组织考试作弊罪",
        "cpws_al_slfy_name": "垫江县人民法院",
        "cpws_al_slfy_sf_name": "重庆市",
        "cpws_al_zs_date": "2024.05.13",
        "cpws_al_ajzh": "（2024）渝0231刑初171号",
        "cpws_al_slcx_name": "一审",
        "cpws_al_cpyz": "　　机动车驾驶资格考试属于刑法第二百八十四条之一规定的“法律规定的国家考试”。在上述考试中组织作弊，符合刑法第二百八十四条之一第一款规定的，应当以组织考试作弊罪定罪处罚。<br/>　　",
        "cpws_al_fyjb_id": "",
        "cpws_al_fyjb_name": "",
        "cpws_al_spnf": "",
        "cpws_al_fbnf": "",
        "cpws_al_fulltext": "",
        "cpws_al_jbaq": "",
        "cpws_al_cpjg": "",
        "cpws_al_cply": "",
        "cpws_al_aljz": "",
        "cpws_al_glsy": "",
        "cpws_al_sub_title": "",
        "cpws_al_is_del": "",
        "cpws_al_infos": "2024-03-1-248-003 / 刑事 / 组织考试作弊罪 / 垫江县人民法院 / 2024.05.13 / （2024）渝0231刑初171号 / 一审 / 入库日期：2024.12.21",
        "cpws_al_fbxx": "",
        "cpws_al_sxcpr": "",
        "cpws_al_pdls": "",
        "sort_num": "27678",
        "cpws_al_add_time": "",
        "cpws_al_rk_time": "2024-12-21 13:14:24",
        "cpws_al_update_time": "",
        "cpws_al_wsxz": "",
        "cpws_al_ts": "03",
        "cpws_al_ts_name": "（刑二庭）",
        "cpws_al_sf": "重庆市",
        "cpws_al_source_id": [
          "0101"
        ],
        "cpws_al_lzgc": "",
        "cpws_al_zdyy": "",
        "cpws_al_jdhg_id": "1245322556467056640",
        "ai_score": 0.0,
        "cpws_al_new_zdxal": ""
      },
      {
        "id": "8UU1lCiAm9i%2BmK9vFSrKamVh9GC4r5DfMaHgQejHE%2B0%3D",
        "cpws_al_id": "8UU1lCiAm9i%2BmK9vFSrKamVh9GC4r5DfMaHgQejHE%2B0%3D",
        "cpws_al_type": "02",
        "cpws_al_status": "01",
        "cpws_al_fb_date": "",
        "cpws_al_no": "2024-04-1-179-022",
        "cpws_al_title": "梁某辉故意伤害案",
        "cpws_al_case_sort_id": [
          "01",
          "A01"
        ],
        "cpws_al_case_sort_name": "刑事",
        "cpws_al_sort_name": "故意伤害罪",
        "cpws_al_slfy_name": "广东省广州市中级人民法院",
        "cpws_al_slfy_sf_name": "广东省",
        "cpws_al_zs_date": "2023.05.11",
        "cpws_al_ajzh": "（2023）粤01刑终456号",
        "cpws_al_slcx_name": "二审",
        "cpws_al_cpyz": "　　明知他人报案而在现场等待，抓捕时无拒捕行为，供认犯罪事实的，应当视为自动投案。其中，明知他人拨打“120”而在现场等待的，考虑到拨打“120”和“110”的联动性，应当认定为“明知他人报案”。“现场”包括案发现场、报警现场或者救助现场等，行为人将被害人送往医院后回到案发现场休息直至被抓获的，可以视为“在现场等待”。<br/>　　",
        "cpws_al_fyjb_id": "",
        "cpws_al_fyjb_name": "",
        "cpws_al_spnf": "",
        "cpws_al_fbnf": "",
        "cpws_al_fulltext": "",
        "cpws_al_jbaq": "",
        "cpws_al_cpjg": "",
        "cpws_al_cply": "",
        "cpws_al_aljz": "",
        "cpws_al_glsy": "",
        "cpws_al_sub_title": "",
        "cpws_al_is_del": "",
        "cpws_al_infos": "2024-04-1-179-022 / 刑事 / 故意伤害罪 / 广东省广州市中级人民法院 / 2023.05.11 / （2023）粤01刑终456号 / 二审 / 入库日期：2024.12.21",
        "cpws_al_fbxx": "",
        "cpws_al_sxcpr": "",
        "cpws_al_pdls": "",
        "sort_num": "27678",
        "cpws_al_add_time": "",
        "cpws_al_rk_time": "2024-12-21 11:34:22",
        "cpws_al_update_time": "",
        "cpws_al_wsxz": "",
        "cpws_al_ts": "04",
        "cpws_al_ts_name": "（刑三庭）",
        "cpws_al_sf": "广东省",
        "cpws_al_source_id": [
          "0101"
        ],
        "cpws_al_lzgc": "",
        "cpws_al_zdyy": "",
        "cpws_al_jdhg_id": "1201922182721048576",
        "ai_score": 0.0,
        "cpws_al_new_zdxal": ""
      },
      {
        "id": "mO6jDYFFcTRVrLiwHOPJ3x68lAwWTIwQMVTkVh%2FWLeY%3D",
        "cpws_al_id": "mO6jDYFFcTRVrLiwHOPJ3x68lAwWTIwQMVTkVh%2FWLeY%3D",
        "cpws_al_type": "02",
        "cpws_al_status": "01",
        "cpws_al_fb_date": "",
        "cpws_al_no": "2024-11-1-348-001",
        "cpws_al_title": "赵某强、辛某宝破坏自然保护地案",
        "cpws_al_case_sort_id": [
          "01",
          "A01"
        ],
        "cpws_al_case_sort_name": "刑事",
        "cpws_al_sort_name": "破坏自然保护地罪",
        "cpws_al_slfy_name": "成都铁路运输第二法院",
        "cpws_al_slfy_sf_name": "四川省",
        "cpws_al_zs_date": "2022.09.23",
        "cpws_al_ajzh": "（2022）川7102刑初35号",
        "cpws_al_slcx_name": "一审",
        "cpws_al_cpyz": "　　违反自然保护地管理法规，在国家公园内盗采矿石，随意弃置固体废物和生活垃圾、破坏植被及使用混凝土硬化路面等，应当认定为刑法第三百四十二条之一第一款规定的“开垦、开发活动”。实施上述行为，造成自然资源破坏、财产损失、人员伤亡、环境损害等后果的，应当认定为“造成严重后果”，构成破坏自然保护地罪；同时构成非法采矿罪等其他犯罪的，依照处罚较重的规定定罪处罚。",
        "cpws_al_fyjb_id": "",
        "cpws_al_fyjb_name": "",
        "cpws_al_spnf": "",
        "cpws_al_fbnf": "",
        "cpws_al_fulltext": "",
        "cpws_al_jbaq": "",
        "cpws_al_cpjg": "",
        "cpws_al_cply": "",
        "cpws_al_aljz": "",
        "cpws_al_glsy": "",
        "cpws_al_sub_title": "",
        "cpws_al_is_del": "",
        "cpws_al_infos": "2024-11-1-348-001 / 刑事 / 破坏自然保护地罪 / 成都铁路运输第二法院 / 2022.09.23 / （2022）川7102刑初35号 / 一审 / 入库日期：2024.12.21 / 修改日期：2025.02.17",
        "cpws_al_fbxx": "",
        "cpws_al_sxcpr": "",
        "cpws_al_pdls": "",
        "sort_num": "27678",
        "cpws_al_add_time": "",
        "cpws_al_rk_time": "2024-12-21 11:14:22",
        "cpws_al_update_time": "2025-02-17 17:45:28",
        "cpws_al_wsxz": "",
        "cpws_al_ts": "11",
        "cpws_al_ts_name": "（环资庭）",
        "cpws_al_sf": "四川省",
        "cpws_al_source_id": [
          "0101"
        ],
        "cpws_al_lzgc": "",
        "cpws_al_zdyy": "",
        "cpws_al_jdhg_id": "1186647586128265216",
        "ai_score": 0.0,
        "cpws_al_new_zdxal": ""
      },
      {
        "id": "LmvSFfXi%2BTxn8knf9nXid3NMz5KU%2FgJQOxuJjRN%2BoXk%3D",
        "cpws_al_id": "LmvSFfXi%2BTxn8knf9nXid3NMz5KU%2FgJQOxuJjRN%2BoXk%3D",
        "cpws_al_type": "02",
        "cpws_al_status": "01",
        "cpws_al_fb_date": "",
        "cpws_al_no": "2024-11-1-340-003",
        "cpws_al_title": "童某胜、杨某污染环境案",
        "cpws_al_case_sort_id": [
          "01",
          "A01"
        ],
        "cpws_al_case_sort_name": "刑事",
        "cpws_al_sort_name": "污染环境罪",
        "cpws_al_slfy_name": "四川省凉山彝族自治州中级人民法院",
        "cpws_al_slfy_sf_name": "四川省",
        "cpws_al_zs_date": "2020.09.04",
        "cpws_al_ajzh": "（2020）川34刑终208号",
        "cpws_al_slcx_name": "二审",
        "cpws_al_cpyz": "　　重点排污单位的环保管理人员、环保设施运维人员等实施篡改、伪造自动监测数据或者干扰自动监测设施，排放化学需氧量、氨氮、二氧化硫、氮氧化物等污染物的，应当认定为刑法第三百三十八条规定的“严重污染环境”，以污染环境罪论处。第三方自动监测设施运维人员主动提出伪造自动监测数据、干扰自动监测设施并积极实施的，依法认定为污染环境罪的主犯。",
        "cpws_al_fyjb_id": "",
        "cpws_al_fyjb_name": "",
        "cpws_al_spnf": "",
        "cpws_al_fbnf": "",
        "cpws_al_fulltext": "",
        "cpws_al_jbaq": "",
        "cpws_al_cpjg": "",
        "cpws_al_cply": "",
        "cpws_al_aljz": "",
        "cpws_al_glsy": "",
        "cpws_al_sub_title": "",
        "cpws_al_is_del": "",
        "cpws_al_infos": "2024-11-1-340-003 / 刑事 / 污染环境罪 / 四川省凉山彝族自治州中级人民法院 / 2020.09.04 / （2020）川34刑终208号 / 二审 / 入库日期：2024.12.21 / 修改日期：2024.12.25",
        "cpws_al_fbxx": "",
        "cpws_al_sxcpr": "",
        "cpws_al_pdls": "",
        "sort_num": "27678",
        "cpws_al_add_time": "",
        "cpws_al_rk_time": "2024-12-21 11:04:41",
        "cpws_al_update_time": "2024-12-25 12:52:24",
        "cpws_al_wsxz": "",
        "cpws_al_ts": "11",
        "cpws_al_ts_name": "（环资庭）",
        "cpws_al_sf": "四川省",
        "cpws_al_source_id": [
          "0101"
        ],
        "cpws_al_lzgc": "",
        "cpws_al_zdyy": "",
        "cpws_al_jdhg_id": "1185266509505626112",
        "ai_score": 0.0,
        "cpws_al_new_zdxal": ""
      },
      {
        "id": "ZNvzvuHwAXifONWbxazE2QF2xWcI5dBqI%2BsfrTMFvRU%3D",
        "cpws_al_id": "ZNvzvuHwAXifONWbxazE2QF2xWcI5dBqI%2BsfrTMFvRU%3D",
        "cpws_al_type": "02",
        "cpws_al_status": "01",
        "cpws_al_fb_date": "",
        "cpws_al_no": "2024-02-1-229-001",
        "cpws_al_title": "卢某洪敲诈勒索案",
        "cpws_al_case_sort_id": [
          "01",
          "A01"
        ],
        "cpws_al_case_sort_name": "刑事",
        "cpws_al_sort_name": "敲诈勒索罪",
        "cpws_al_slfy_name": "佛山市南海区人民法院",
        "cpws_al_slfy_sf_name": "广东省",
        "cpws_al_zs_date": "2015.10.11",
        "cpws_al_ajzh": "(2014)佛南法刑初字第3321号",
        "cpws_al_slcx_name": "一审",
        "cpws_al_cpyz": "　　共同犯罪中，部分参与人实施了共同故意以外的犯罪行为，其他参与人对超出共同故意的行为不知情且没有共同实施的，其他参与人不应对此承担刑事责任。实行犯的行为超出共同犯意的范围，由此造成的结果应当由具体行为人承担刑事责任。<br/>　　",
        "cpws_al_fyjb_id": "",
        "cpws_al_fyjb_name": "",
        "cpws_al_spnf": "",
        "cpws_al_fbnf": "",
        "cpws_al_fulltext": "",
        "cpws_al_jbaq": "",
        "cpws_al_cpjg": "",
        "cpws_al_cply": "",
        "cpws_al_aljz": "",
        "cpws_al_glsy": "",
        "cpws_al_sub_title": "",
        "cpws_al_is_del": "",
        "cpws_al_infos": "2024-02-1-229-001 / 刑事 / 敲诈勒索罪 / 佛山市南海区人民法院 / 2015.10.11 / (2014)佛南法刑初字第3321号 / 一审 / 入库日期：2024.12.21",
        "cpws_al_fbxx": "",
        "cpws_al_sxcpr": "",
        "cpws_al_pdls": "",
        "sort_num": "27678",
        "cpws_al_add_time": "",
        "cpws_al_rk_time": "2024-12-21 10:34:22",
        "cpws_al_update_time": "",
        "cpws_al_wsxz": "",
        "cpws_al_ts": "02",
        "cpws_al_ts_name": "（刑一庭）",
        "cpws_al_sf": "广东省",
        "cpws_al_source_id": [
          "0101"
        ],
        "cpws_al_lzgc": "",
        "cpws_al_zdyy": "",
        "cpws_al_jdhg_id": "1272569095409115136",
        "ai_score": 0.0,
        "cpws_al_new_zdxal": ""
      },
      {
        "id": "MgfMpsojeWg67jOWoo22Kqj0jUOA0xI2y0VYKy9V9lk%3D",
        "cpws_al_id": "MgfMpsojeWg67jOWoo22Kqj0jUOA0xI2y0VYKy9V9lk%3D",
        "cpws_al_type": "02",
        "cpws_al_status": "01",
        "cpws_al_fb_date": "",
        "cpws_al_no": "2024-04-1-134-005",
        "cpws_al_title": "赵某杰集资诈骗案",
        "cpws_al_case_sort_id": [
          "01",
          "A01"
        ],
        "cpws_al_case_sort_name": "刑事",
        "cpws_al_sort_name": "集资诈骗罪",
        "cpws_al_slfy_name": "天津市第二中级人民法院",
        "cpws_al_slfy_sf_name": "天津市",
        "cpws_al_zs_date": "2019.10.24",
        "cpws_al_ajzh": "（2019）津02刑终281号",
        "cpws_al_slcx_name": "二审",
        "cpws_al_cpyz": "　　    行为人非法吸收投资款后，未用于经营活动，对投资款肆意处分，偿还个人债务，以借新还旧的方式归还本息，在明知严重亏损的情况下，继续以同样的方式吸收投资款，且在投资款无法兑付后又逃匿的，应当认定其主观上具有非法占有目的，依法以集资诈骗罪论处。<br/>　　",
        "cpws_al_fyjb_id": "",
        "cpws_al_fyjb_name": "",
        "cpws_al_spnf": "",
        "cpws_al_fbnf": "",
        "cpws_al_fulltext": "",
        "cpws_al_jbaq": "",
        "cpws_al_cpjg": "",
        "cpws_al_cply": "",
        "cpws_al_aljz": "",
        "cpws_al_glsy": "",
        "cpws_al_sub_title": "",
        "cpws_al_is_del": "",
        "cpws_al_infos": "2024-04-1-134-005 / 刑事 / 集资诈骗罪 / 天津市第二中级人民法院 / 2019.10.24 / （2019）津02刑终281号 / 二审 / 入库日期：2024.12.21",
        "cpws_al_fbxx": "",
        "cpws_al_sxcpr": "",
        "cpws_al_pdls": "",
        "sort_num": "27678",
        "cpws_al_add_time": "",
        "cpws_al_rk_time": "2024-12-21 10:14:22",
        "cpws_al_update_time": "",
        "cpws_al_wsxz": "",
        "cpws_al_ts": "04",
        "cpws_al_ts_name": "（刑三庭）",
        "cpws_al_sf": "天津市",
        "cpws_al_source_id": [
          "0101"
        ],
        "cpws_al_lzgc": "",
        "cpws_al_zdyy": "",
        "cpws_al_jdhg_id": "1289905386400256000",
        "ai_score": 0.0,
        "cpws_al_new_zdxal": ""
      },
      {
        "id": "K1H1P%2B5cYZQ%2BU0HzULVHFxoItpZ3sZUFj5yZb81o4JM%3D",
        "cpws_al_id": "K1H1P%2B5cYZQ%2BU0HzULVHFxoItpZ3sZUFj5yZb81o4JM%3D",
        "cpws_al_type": "02",
        "cpws_al_status": "01",
        "cpws_al_fb_date": "",
        "cpws_al_no": "2024-04-1-182-001",
        "cpws_al_title": "王某某强奸、猥亵儿童、强制猥亵、聚众淫乱案",
        "cpws_al_case_sort_id": [
          "01",
          "A01"
        ],
        "cpws_al_case_sort_name": "刑事",
        "cpws_al_sort_name": "强奸罪",
        "cpws_al_slfy_name": "山东省高级人民法院",
        "cpws_al_slfy_sf_name": "山东省",
        "cpws_al_zs_date": "2023.04.07",
        "cpws_al_ajzh": "",
        "cpws_al_slcx_name": "其他审理程序",
        "cpws_al_cpyz": "　　行为人在网络平台上以交友、聊天、谈朋友、辅导、教学、发红包、介绍明星或其他资源等方式，骗取未成年人特别是幼女的信任后，针对未成年人实施强奸、强制猥亵、猥亵儿童等性侵未成年人犯罪的，危害面更广、危害性更大，应当依法严惩。",
        "cpws_al_fyjb_id": "",
        "cpws_al_fyjb_name": "",
        "cpws_al_spnf": "",
        "cpws_al_fbnf": "",
        "cpws_al_fulltext": "",
        "cpws_al_jbaq": "",
        "cpws_al_cpjg": "",
        "cpws_al_cply": "",
        "cpws_al_aljz": "",
        "cpws_al_glsy": "",
        "cpws_al_sub_title": "",
        "cpws_al_is_del": "",
        "cpws_al_infos": "2024-04-1-182-001 / 刑事 / 强奸罪 / 山东省高级人民法院 / 2023.04.07 / 其他审理程序 / 入库日期：2024.12.21 / 修改日期：2025.05.20",
        "cpws_al_fbxx": "",
        "cpws_al_sxcpr": "",
        "cpws_al_pdls": "",
        "sort_num": "27678",
        "cpws_al_add_time": "",
        "cpws_al_rk_time": "2024-12-21 10:04:26",
        "cpws_al_update_time": "2025-05-20 10:00:00",
        "cpws_al_wsxz": "",
        "cpws_al_ts": "04",
        "cpws_al_ts_name": "（刑三庭）",
        "cpws_al_group": [
          "01"
        ],
        "fx_cpws_al_glsy": "",
        "cpws_al_sf": "山东省",
        "cpws_al_source_id": [
          "0101"
        ],
        "cpws_al_lzgc": "",
        "cpws_al_zdyy": "",
        "cpws_al_jdhg_id": "1290266171081240576",
        "ai_score": 0.0,
        "cpws_al_new_zdxal": ""
      },
      {
        "id": "svPdtLjbfXV9hd%2BiCjCjiK5gNFgpATYx7fAuCCzkEMc%3D",
        "cpws_al_id": "svPdtLjbfXV9hd%2BiCjCjiK5gNFgpATYx7fAuCCzkEMc%3D",
        "cpws_al_type": "02",
        "cpws_al_status": "01",
        "cpws_al_fb_date": "",
        "cpws_al_no": "2024-02-1-067-004",
        "cpws_al_title": "李某钦生产、销售伪劣产品案",
        "cpws_al_case_sort_id": [
          "01",
          "A01"
        ],
        "cpws_al_case_sort_name": "刑事",
        "cpws_al_sort_name": "生产、销售伪劣产品罪",
        "cpws_al_slfy_name": "温州市鹿城区人民法院",
        "cpws_al_slfy_sf_name": "浙江省",
        "cpws_al_zs_date": "2024.04.27",
        "cpws_al_ajzh": "（2023）浙0302刑初87号",
        "cpws_al_slcx_name": "一审",
        "cpws_al_cpyz": "　　    根据刑法第一百四十九条第一款和《最高人民法院、最高人民检察院关于办理危害食品安全刑事案件适用法律若干问题的解释》（法释〔2021〕24号）第十三条第二款的规定，生产、销售不符合食品安全标准的食品，无证据证明足以造成严重食物中毒事故或者其他严重食源性疾病，不构成生产、销售不符合安全标准的食品罪，但是销售金额达到五万元以上的，依照生产、销售伪劣产品罪定罪处罚。<br/>　　",
        "cpws_al_fyjb_id": "",
        "cpws_al_fyjb_name": "",
        "cpws_al_spnf": "",
        "cpws_al_fbnf": "",
        "cpws_al_fulltext": "",
        "cpws_al_jbaq": "",
        "cpws_al_cpjg": "",
        "cpws_al_cply": "",
        "cpws_al_aljz": "",
        "cpws_al_glsy": "",
        "cpws_al_sub_title": "",
        "cpws_al_is_del": "",
        "cpws_al_infos": "2024-02-1-067-004 / 刑事 / 生产、销售伪劣产品罪 / 温州市鹿城区人民法院 / 2024.04.27 / （2023）浙0302刑初87号 / 一审 / 入库日期：2024.12.21",
        "cpws_al_fbxx": "",
        "cpws_al_sxcpr": "",
        "cpws_al_pdls": "",
        "sort_num": "27678",
        "cpws_al_add_time": "",
        "cpws_al_rk_time": "2024-12-21 09:44:22",
        "cpws_al_update_time": "",
        "cpws_al_wsxz": "",
        "cpws_al_ts": "02",
        "cpws_al_ts_name": "（刑一庭）",
        "cpws_al_sf": "浙江省",
        "cpws_al_source_id": [
          "0101"
        ],
        "cpws_al_lzgc": "",
        "cpws_al_zdyy": "",
        "cpws_al_jdhg_id": "1313217449096650752",
        "ai_score": 0.0,
        "cpws_al_new_zdxal": ""
      },
      {
        "id": "Miy1OPWf4rNUrXbcrsLjf6beIYVuJjebTdRN%2FSP1bA4%3D",
        "cpws_al_id": "Miy1OPWf4rNUrXbcrsLjf6beIYVuJjebTdRN%2FSP1bA4%3D",
        "cpws_al_type": "02",
        "cpws_al_status": "01",
        "cpws_al_fb_date": "",
        "cpws_al_no": "2024-02-1-072-006",
        "cpws_al_title": "孙某结等生产、销售有毒、有害食品案",
        "cpws_al_case_sort_id": [
          "01",
          "A01"
        ],
        "cpws_al_case_sort_name": "刑事",
        "cpws_al_sort_name": "生产、销售有毒、有害食品罪",
        "cpws_al_slfy_name": "昆山市人民法院",
        "cpws_al_slfy_sf_name": "江苏省",
        "cpws_al_zs_date": "2023.03.31",
        "cpws_al_ajzh": "（2022）苏0583刑初161号",
        "cpws_al_slcx_name": "一审",
        "cpws_al_cpyz": "　　    工业用甲醛因危害人体健康，被列入国务院有关部门发布的《食品中可能违法添加的非食用物质名单》，行为人在生产、销售的食品中掺入工业用甲醛或者销售明知掺有工业用甲醛的食品的，应以生产、销售有毒、有害食品罪定罪处罚。<br/>　　",
        "cpws_al_fyjb_id": "",
        "cpws_al_fyjb_name": "",
        "cpws_al_spnf": "",
        "cpws_al_fbnf": "",
        "cpws_al_fulltext": "",
        "cpws_al_jbaq": "",
        "cpws_al_cpjg": "",
        "cpws_al_cply": "",
        "cpws_al_aljz": "",
        "cpws_al_glsy": "",
        "cpws_al_sub_title": "",
        "cpws_al_is_del": "",
        "cpws_al_infos": "2024-02-1-072-006 / 刑事 / 生产、销售有毒、有害食品罪 / 昆山市人民法院 / 2023.03.31 / （2022）苏0583刑初161号 / 一审 / 入库日期：2024.12.20",
        "cpws_al_fbxx": "",
        "cpws_al_sxcpr": "",
        "cpws_al_pdls": "",
        "sort_num": "27678",
        "cpws_al_add_time": "",
        "cpws_al_rk_time": "2024-12-20 17:54:22",
        "cpws_al_update_time": "",
        "cpws_al_wsxz": "",
        "cpws_al_ts": "02",
        "cpws_al_ts_name": "（刑一庭）",
        "cpws_al_sf": "江苏省",
        "cpws_al_source_id": [
          "0101"
        ],
        "cpws_al_lzgc": "",
        "cpws_al_zdyy": "",
        "cpws_al_jdhg_id": "1313154964758994944",
        "ai_score": 0.0,
        "cpws_al_new_zdxal": ""
      },
      {
        "id": "hRbr%2FVEJ5OEGj%2FW4QsucAf%2FZPIO8VloCoukbvG1ihyo%3D",
        "cpws_al_id": "hRbr%2FVEJ5OEGj%2FW4QsucAf%2FZPIO8VloCoukbvG1ihyo%3D",
        "cpws_al_type": "02",
        "cpws_al_status": "01",
        "cpws_al_fb_date": "",
        "cpws_al_no": "2024-06-1-055-028",
        "cpws_al_title": "汪某秋危险驾驶案",
        "cpws_al_case_sort_id": [
          "01",
          "A01"
        ],
        "cpws_al_case_sort_name": "刑事",
        "cpws_al_sort_name": "危险驾驶罪",
        "cpws_al_slfy_name": "淳安县人民法院",
        "cpws_al_slfy_sf_name": "浙江省",
        "cpws_al_zs_date": "2024.03.14",
        "cpws_al_ajzh": "浙0127刑初46号",
        "cpws_al_slcx_name": "一审",
        "cpws_al_cpyz": "　　《最高人民法院、最高人民检察院、公安部、司法部关于办理醉酒危险驾驶刑事案件的意见》（高检发办字〔2023〕187号）第十四条第八项将“五年内曾因饮酒后驾驶机动车被查获或者受过行政处罚”规定为一般不适用缓刑的情形。从统一执法司法标准和有利于被告人角度考虑，应当自行为人实施上一次饮酒后驾驶机动车行为之日起计算“五年内”的区间，而不以受到行政处罚之日起计算。<br/>　　",
        "cpws_al_fyjb_id": "",
        "cpws_al_fyjb_name": "",
        "cpws_al_spnf": "",
        "cpws_al_fbnf": "",
        "cpws_al_fulltext": "",
        "cpws_al_jbaq": "",
        "cpws_al_cpjg": "",
        "cpws_al_cply": "",
        "cpws_al_aljz": "",
        "cpws_al_glsy": "",
        "cpws_al_sub_title": "",
        "cpws_al_is_del": "",
        "cpws_al_infos": "2024-06-1-055-028 / 刑事 / 危险驾驶罪 / 淳安县人民法院 / 2024.03.14 / 浙0127刑初46号 / 一审 / 入库日期：2024.12.20",
        "cpws_al_fbxx": "",
        "cpws_al_sxcpr": "",
        "cpws_al_pdls": "",
        "sort_num": "27678",
        "cpws_al_add_time": "",
        "cpws_al_rk_time": "2024-12-20 17:44:58",
        "cpws_al_update_time": "",
        "cpws_al_wsxz": "",
        "cpws_al_ts": "06",
        "cpws_al_ts_name": "（刑五庭）",
        "cpws_al_sf": "浙江省",
        "cpws_al_source_id": [
          "0101"
        ],
        "cpws_al_lzgc": "",
        "cpws_al_zdyy": "",
        "cpws_al_jdhg_id": "1259913080976969728",
        "ai_score": 0.0,
        "cpws_al_new_zdxal": ""
      },
      {
        "id": "btfRH%2FDtwcN5oLhDuRK5TKh2xSKpkPDDL1d%2B3pbffKg%3D",
        "cpws_al_id": "btfRH%2FDtwcN5oLhDuRK5TKh2xSKpkPDDL1d%2B3pbffKg%3D",
        "cpws_al_type": "02",
        "cpws_al_status": "01",
        "cpws_al_fb_date": "",
        "cpws_al_no": "2024-06-1-054-002",
        "cpws_al_title": "黄某树交通肇事案",
        "cpws_al_case_sort_id": [
          "01",
          "A01"
        ],
        "cpws_al_case_sort_name": "刑事",
        "cpws_al_sort_name": "交通肇事罪",
        "cpws_al_slfy_name": "广安市广安区人民法院",
        "cpws_al_slfy_sf_name": "四川省",
        "cpws_al_zs_date": "2022.07.12",
        "cpws_al_ajzh": "(2022)川1602刑初119",
        "cpws_al_slcx_name": "一审",
        "cpws_al_cpyz": "　　    行为人驾驶机动车将被害人撞倒于道路中央无法动弹后逃逸，致被害人被后来车辆二次碰撞，前后两次碰撞共同导致被害人死亡的，第二次碰撞不阻断行为人交通肇事后逃逸与被害人死亡结果之间的因果关系，应当认定行为人“因逃逸致人死亡”。<br/>　　",
        "cpws_al_fyjb_id": "",
        "cpws_al_fyjb_name": "",
        "cpws_al_spnf": "",
        "cpws_al_fbnf": "",
        "cpws_al_fulltext": "",
        "cpws_al_jbaq": "",
        "cpws_al_cpjg": "",
        "cpws_al_cply": "",
        "cpws_al_aljz": "",
        "cpws_al_glsy": "",
        "cpws_al_sub_title": "",
        "cpws_al_is_del": "",
        "cpws_al_infos": "2024-06-1-054-002 / 刑事 / 交通肇事罪 / 广安市广安区人民法院 / 2022.07.12 / (2022)川1602刑初119 / 一审 / 入库日期：2024.12.20",
        "cpws_al_fbxx": "",
        "cpws_al_sxcpr": "",
        "cpws_al_pdls": "",
        "sort_num": "27678",
        "cpws_al_add_time": "",
        "cpws_al_rk_time": "2024-12-20 17:44:57",
        "cpws_al_update_time": "",
        "cpws_al_wsxz": "",
        "cpws_al_ts": "06",
        "cpws_al_ts_name": "（刑五庭）",
        "cpws_al_sf": "四川省",
        "cpws_al_source_id": [
          "0101"
        ],
        "cpws_al_lzgc": "",
        "cpws_al_zdyy": "",
        "cpws_al_jdhg_id": "1188812927298174976",
        "ai_score": 0.0,
        "cpws_al_new_zdxal": ""
      },
      {
        "id": "7CCZD6JjazEgeR2ENMaDzY2FYEoNocXRvM2AbVXRtkQ%3D",
        "cpws_al_id": "7CCZD6JjazEgeR2ENMaDzY2FYEoNocXRvM2AbVXRtkQ%3D",
        "cpws_al_type": "02",
        "cpws_al_status": "01",
        "cpws_al_fb_date": "",
        "cpws_al_no": "2024-06-1-055-027",
        "cpws_al_title": "马某危险驾驶案",
        "cpws_al_case_sort_id": [
          "01",
          "A01"
        ],
        "cpws_al_case_sort_name": "刑事",
        "cpws_al_sort_name": "危险驾驶罪",
        "cpws_al_slfy_name": "北京市通州区人民法院",
        "cpws_al_slfy_sf_name": "北京市",
        "cpws_al_zs_date": "2024.03.07",
        "cpws_al_ajzh": "（2024）京0112刑初299号",
        "cpws_al_slcx_name": "一审",
        "cpws_al_cpyz": "　　     因醉酒驾驶造成交通事故且负事故全部或者主要责任的被告人未赔偿损失的，一般不适用缓刑。但是，因事故相对方要求的赔偿数额明显超出合理范围，且拒不提供相应损失证明，经调解双方未能就赔偿数额达成一致的，不属于前述因“未赔偿损失”而一般不适用缓刑的情形，对被告人可依法适用缓刑。<br/>　　",
        "cpws_al_fyjb_id": "",
        "cpws_al_fyjb_name": "",
        "cpws_al_spnf": "",
        "cpws_al_fbnf": "",
        "cpws_al_fulltext": "",
        "cpws_al_jbaq": "",
        "cpws_al_cpjg": "",
        "cpws_al_cply": "",
        "cpws_al_aljz": "",
        "cpws_al_glsy": "",
        "cpws_al_sub_title": "",
        "cpws_al_is_del": "",
        "cpws_al_infos": "2024-06-1-055-027 / 刑事 / 危险驾驶罪 / 北京市通州区人民法院 / 2024.03.07 / （2024）京0112刑初299号 / 一审 / 入库日期：2024.12.20",
        "cpws_al_fbxx": "",
        "cpws_al_sxcpr": "",
        "cpws_al_pdls": "",
        "sort_num": "27678",
        "cpws_al_add_time": "",
        "cpws_al_rk_time": "2024-12-20 17:44:56",
        "cpws_al_update_time": "",
        "cpws_al_wsxz": "",
        "cpws_al_ts": "06",
        "cpws_al_ts_name": "（刑五庭）",
        "cpws_al_sf": "北京市",
        "cpws_al_source_id": [
          "0101"
        ],
        "cpws_al_lzgc": "",
        "cpws_al_zdyy": "",
        "cpws_al_jdhg_id": "1259937300666650624",
        "ai_score": 0.0,
        "cpws_al_new_zdxal": ""
      },
      {
        "id": "ruhSnfoJRU2rrsmNC%2FyMXvigDzHkC%2Fezl%2BdThN%2BTYA4%3D",
        "cpws_al_id": "ruhSnfoJRU2rrsmNC%2FyMXvigDzHkC%2Fezl%2BdThN%2BTYA4%3D",
        "cpws_al_type": "02",
        "cpws_al_status": "01",
        "cpws_al_fb_date": "",
        "cpws_al_no": "2024-05-1-017-001",
        "cpws_al_title": "叶某某、舒某某以危险方法危害公共安全案",
        "cpws_al_case_sort_id": [
          "01",
          "A01"
        ],
        "cpws_al_case_sort_name": "刑事",
        "cpws_al_sort_name": "以危险方法危害公共安全罪",
        "cpws_al_slfy_name": "四川省成都市中级人民法院",
        "cpws_al_slfy_sf_name": "四川省",
        "cpws_al_zs_date": "2022.05.05",
        "cpws_al_ajzh": "（2022）川01刑终310号",
        "cpws_al_slcx_name": "二审",
        "cpws_al_cpyz": "　　    行为人违反道路交通安全法规，驾驶机动车在高速路上追逐竞驶，置不特定多数人的生命、健康及公私财产安全于不顾，构成以危险方法危害公共安全罪。在主观故意上，由于行为人对其行为可能会发生危害公共安全后果是明知的且持放任态度，应当认定为故意犯罪。<br/>　　",
        "cpws_al_fyjb_id": "",
        "cpws_al_fyjb_name": "",
        "cpws_al_spnf": "",
        "cpws_al_fbnf": "",
        "cpws_al_fulltext": "",
        "cpws_al_jbaq": "",
        "cpws_al_cpjg": "",
        "cpws_al_cply": "",
        "cpws_al_aljz": "",
        "cpws_al_glsy": "",
        "cpws_al_sub_title": "",
        "cpws_al_is_del": "",
        "cpws_al_infos": "2024-05-1-017-001 / 刑事 / 以危险方法危害公共安全罪 / 四川省成都市中级人民法院 / 2022.05.05 / （2022）川01刑终310号 / 二审 / 入库日期：2024.12.20",
        "cpws_al_fbxx": "",
        "cpws_al_sxcpr": "",
        "cpws_al_pdls": "",
        "sort_num": "27678",
        "cpws_al_add_time": "",
        "cpws_al_rk_time": "2024-12-20 17:44:52",
        "cpws_al_update_time": "",
        "cpws_al_wsxz": "",
        "cpws_al_ts": "05",
        "cpws_al_ts_name": "（刑四庭）",
        "cpws_al_sf": "四川省",
        "cpws_al_source_id": [
          "0101"
        ],
        "cpws_al_lzgc": "",
        "cpws_al_zdyy": "",
        "cpws_al_jdhg_id": "1187809558492348416",
        "ai_score": 0.0,
        "cpws_al_new_zdxal": ""
      },
      {
        "id": "Y8tDTMZzpE61VdNSIBLPY9qoh0vQcOeUgPsRWVEggaU%3D",
        "cpws_al_id": "Y8tDTMZzpE61VdNSIBLPY9qoh0vQcOeUgPsRWVEggaU%3D",
        "cpws_al_type": "02",
        "cpws_al_status": "01",
        "cpws_al_fb_date": "",
        "cpws_al_no": "2024-02-1-072-005",
        "cpws_al_title": "陈某辉生产、销售有毒、有害食品案",
        "cpws_al_case_sort_id": [
          "01",
          "A01"
        ],
        "cpws_al_case_sort_name": "刑事",
        "cpws_al_sort_name": "生产、销售有毒、有害食品罪",
        "cpws_al_slfy_name": "上海铁路运输法院",
        "cpws_al_slfy_sf_name": "上海市",
        "cpws_al_zs_date": "2022.09.14",
        "cpws_al_ajzh": "（2022）沪7101刑初172号",
        "cpws_al_slcx_name": "一审",
        "cpws_al_cpyz": "　　    碱性橙Ⅱ（俗称“黄粉”“王金黄”“块黄”），属于工业染料，被列入国务院有关部门发布的《食品中可能违法添加的非食用物质名单》。根据《最高人民法院、最高人民检察院关于办理危害食品安全刑事案件适用法律若干问题的解释》（法释〔2021〕24号）第九条第二项规定，行为人在生产、销售的食品中掺入含有碱性橙Ⅱ成分的工业染料，或者销售明知掺有碱性橙Ⅱ成分的食品的，应当以生产、销售有毒、有害食品罪定罪处罚。<br/>　　",
        "cpws_al_fyjb_id": "",
        "cpws_al_fyjb_name": "",
        "cpws_al_spnf": "",
        "cpws_al_fbnf": "",
        "cpws_al_fulltext": "",
        "cpws_al_jbaq": "",
        "cpws_al_cpjg": "",
        "cpws_al_cply": "",
        "cpws_al_aljz": "",
        "cpws_al_glsy": "",
        "cpws_al_sub_title": "",
        "cpws_al_is_del": "",
        "cpws_al_infos": "2024-02-1-072-005 / 刑事 / 生产、销售有毒、有害食品罪 / 上海铁路运输法院 / 2022.09.14 / （2022）沪7101刑初172号 / 一审 / 入库日期：2024.12.20",
        "cpws_al_fbxx": "",
        "cpws_al_sxcpr": "",
        "cpws_al_pdls": "",
        "sort_num": "27678",
        "cpws_al_add_time": "",
        "cpws_al_rk_time": "2024-12-20 17:14:52",
        "cpws_al_update_time": "",
        "cpws_al_wsxz": "",
        "cpws_al_ts": "02",
        "cpws_al_ts_name": "（刑一庭）",
        "cpws_al_sf": "上海市",
        "cpws_al_source_id": [
          "0101"
        ],
        "cpws_al_lzgc": "",
        "cpws_al_zdyy": "",
        "cpws_al_jdhg_id": "1313219152890040320",
        "ai_score": 0.0,
        "cpws_al_new_zdxal": ""
      },
      {
        "id": "OQZN0%2F72d8PN%2FBVWE7WHtqRokYixdT6B8jMb836nRLQ%3D",
        "cpws_al_id": "OQZN0%2F72d8PN%2FBVWE7WHtqRokYixdT6B8jMb836nRLQ%3D",
        "cpws_al_type": "02",
        "cpws_al_status": "01",
        "cpws_al_fb_date": "",
        "cpws_al_no": "2024-04-1-257-002",
        "cpws_al_title": "翟某可帮助信息网络犯罪活动案",
        "cpws_al_case_sort_id": [
          "01",
          "A01"
        ],
        "cpws_al_case_sort_name": "刑事",
        "cpws_al_sort_name": "帮助信息网络犯罪活动罪",
        "cpws_al_slfy_name": "陕西省西安市中级人民法院",
        "cpws_al_slfy_sf_name": "陕西省",
        "cpws_al_zs_date": "2024.06.03",
        "cpws_al_ajzh": "（2024）陕01刑终326号",
        "cpws_al_slcx_name": "二审",
        "cpws_al_cpyz": "　　<p>为他人实施电信网络诈骗而提供话务支持等帮助行为，但未与被帮助者就诈骗犯罪进行通谋，未实际参与后续实施的诈骗犯罪，亦未参与违法所得分成的，可以适用刑法第二百八十七条之二的规定，以帮助信息网络犯罪活动罪论处。</p>",
        "cpws_al_fyjb_id": "",
        "cpws_al_fyjb_name": "",
        "cpws_al_spnf": "",
        "cpws_al_fbnf": "",
        "cpws_al_fulltext": "",
        "cpws_al_jbaq": "",
        "cpws_al_cpjg": "",
        "cpws_al_cply": "",
        "cpws_al_aljz": "",
        "cpws_al_glsy": "",
        "cpws_al_sub_title": "",
        "cpws_al_is_del": "",
        "cpws_al_infos": "2024-04-1-257-002 / 刑事 / 帮助信息网络犯罪活动罪 / 陕西省西安市中级人民法院 / 2024.06.03 / （2024）陕01刑终326号 / 二审 / 入库日期：2024.12.19 / 修改日期：2025.06.12",
        "cpws_al_fbxx": "",
        "cpws_al_sxcpr": "",
        "cpws_al_pdls": "",
        "sort_num": "27675",
        "cpws_al_add_time": "",
        "cpws_al_rk_time": "2024-12-19 09:57:24",
        "cpws_al_update_time": "2025-06-12 15:36:37",
        "cpws_al_wsxz": "",
        "cpws_al_ts": "04",
        "cpws_al_ts_name": "（刑三庭）",
        "cpws_al_group": [],
        "cpws_al_sf": "陕西省",
        "cpws_al_source_id": [
          "0101"
        ],
        "cpws_al_lzgc": "",
        "cpws_al_zdyy": "",
        "cpws_al_jdhg_id": "1319455657191026688",
        "ai_score": 0.0,
        "cpws_al_new_zdxal": ""
      },
      {
        "id": "DS6uMBZlueH5BPtbqrQmMVNYJEcG1Gzd9qEfYaPJo6c%3D",
        "cpws_al_id": "DS6uMBZlueH5BPtbqrQmMVNYJEcG1Gzd9qEfYaPJo6c%3D",
        "cpws_al_type": "02",
        "cpws_al_status": "01",
        "cpws_al_fb_date": "",
        "cpws_al_no": "2024-11-1-349-007",
        "cpws_al_title": " 徐某旭非法采矿刑事附带民事公益诉讼案",
        "cpws_al_case_sort_id": [
          "01",
          "A01"
        ],
        "cpws_al_case_sort_name": "刑事",
        "cpws_al_sort_name": "非法采矿罪",
        "cpws_al_slfy_name": "河北雄安新区中级人民法院",
        "cpws_al_slfy_sf_name": "河北省",
        "cpws_al_zs_date": "2023.09.28",
        "cpws_al_ajzh": "（2023）冀96刑终37号",
        "cpws_al_slcx_name": "二审",
        "cpws_al_cpyz": "　　多名侵权人前后对一地施破坏生态环境侵权行为，已到案侵权行为人仅对自己破坏的部分实施修复难以实现生态环境的整体修复的，可由国家规定的机关或者法律规定的组织委托具有专门修复能力或资质的单位进行修复；人民法院在确定整体修复方案和费用的基础上，根据单一侵权人破坏比例判定其承担相应的修复费用。",
        "cpws_al_fyjb_id": "",
        "cpws_al_fyjb_name": "",
        "cpws_al_spnf": "",
        "cpws_al_fbnf": "",
        "cpws_al_fulltext": "",
        "cpws_al_jbaq": "",
        "cpws_al_cpjg": "",
        "cpws_al_cply": "",
        "cpws_al_aljz": "",
        "cpws_al_glsy": "",
        "cpws_al_sub_title": "",
        "cpws_al_is_del": "",
        "cpws_al_infos": "2024-11-1-349-007 / 刑事 / 非法采矿罪 / 河北雄安新区中级人民法院 / 2023.09.28 / （2023）冀96刑终37号 / 二审 / 入库日期：2024.12.15",
        "cpws_al_fbxx": "",
        "cpws_al_sxcpr": "",
        "cpws_al_pdls": "",
        "sort_num": "27675",
        "cpws_al_add_time": "",
        "cpws_al_rk_time": "2024-12-15 14:24:23",
        "cpws_al_update_time": "",
        "cpws_al_wsxz": "",
        "cpws_al_ts": "11",
        "cpws_al_ts_name": "（环资庭）",
        "cpws_al_sf": "河北省",
        "cpws_al_source_id": [
          "0101"
        ],
        "cpws_al_lzgc": "",
        "cpws_al_zdyy": "",
        "cpws_al_jdhg_id": "1209080643913261056",
        "ai_score": 0.0,
        "cpws_al_new_zdxal": ""
      },
      {
        "id": "Upf4Aacl%2Bwf%2Bhv7RH3MF9AqLU60ULSj7NnOZQta6KXE%3D",
        "cpws_al_id": "Upf4Aacl%2Bwf%2Bhv7RH3MF9AqLU60ULSj7NnOZQta6KXE%3D",
        "cpws_al_type": "02",
        "cpws_al_status": "01",
        "cpws_al_fb_date": "",
        "cpws_al_no": "2024-04-1-253-001",
        "cpws_al_title": "余某等提供侵入、非法控制计算机信息系统程序、工具案",
        "cpws_al_case_sort_id": [
          "01",
          "A01"
        ],
        "cpws_al_case_sort_name": "刑事",
        "cpws_al_sort_name": "提供侵入、非法控制计算机信息系统程序、工具罪",
        "cpws_al_slfy_name": "重庆市南岸区人民法院",
        "cpws_al_slfy_sf_name": "重庆市",
        "cpws_al_zs_date": "2021.01.01",
        "cpws_al_ajzh": "（2019）渝0108刑初873号",
        "cpws_al_slcx_name": "一审",
        "cpws_al_cpyz": "　　软件著作权的登记审查为形式性审查，其主要是对技术或产品成果的独创性进行确认，并不对软件用途的合法性进行认定。涉案软件已取得著作权的，不影响对提供侵入、非法控制计算机信息系统程序、工具罪的认定。<br/>　　",
        "cpws_al_fyjb_id": "",
        "cpws_al_fyjb_name": "",
        "cpws_al_spnf": "",
        "cpws_al_fbnf": "",
        "cpws_al_fulltext": "",
        "cpws_al_jbaq": "",
        "cpws_al_cpjg": "",
        "cpws_al_cply": "",
        "cpws_al_aljz": "",
        "cpws_al_glsy": "",
        "cpws_al_sub_title": "",
        "cpws_al_is_del": "",
        "cpws_al_infos": "2024-04-1-253-001 / 刑事 / 提供侵入、非法控制计算机信息系统程序、工具罪 / 重庆市南岸区人民法院 / 2021.01.01 / （2019）渝0108刑初873号 / 一审 / 入库日期：2024.12.12",
        "cpws_al_fbxx": "",
        "cpws_al_sxcpr": "",
        "cpws_al_pdls": "",
        "sort_num": "27675",
        "cpws_al_add_time": "",
        "cpws_al_rk_time": "2024-12-12 17:34:22",
        "cpws_al_update_time": "",
        "cpws_al_wsxz": "",
        "cpws_al_ts": "04",
        "cpws_al_ts_name": "（刑三庭）",
        "cpws_al_sf": "重庆市",
        "cpws_al_source_id": [
          "0101"
        ],
        "cpws_al_lzgc": "",
        "cpws_al_zdyy": "",
        "cpws_al_jdhg_id": "1225132116090560512",
        "ai_score": 0.0,
        "cpws_al_new_zdxal": ""
      },
      {
        "id": "qHvZdfLucVvoTPhNhuqcd%2Fa7MlBcG15ON%2BHzBHOqHmI%3D",
        "cpws_al_id": "qHvZdfLucVvoTPhNhuqcd%2Fa7MlBcG15ON%2BHzBHOqHmI%3D",
        "cpws_al_type": "02",
        "cpws_al_status": "01",
        "cpws_al_fb_date": "",
        "cpws_al_no": "2024-04-1-207-004",
        "cpws_al_title": "袁某、郭某冰侵犯公民个人信息案",
        "cpws_al_case_sort_id": [
          "01",
          "A01"
        ],
        "cpws_al_case_sort_name": "刑事",
        "cpws_al_sort_name": "侵犯公民个人信息罪",
        "cpws_al_slfy_name": "四川省泸州市中级人民法院",
        "cpws_al_slfy_sf_name": "四川省",
        "cpws_al_zs_date": "2020.11.19",
        "cpws_al_ajzh": "（2020）川05刑终124号",
        "cpws_al_slcx_name": "二审",
        "cpws_al_cpyz": "　　      企业支付宝账户除企业账户信息外，还记载了企业法定代表人的手机号、身份证号码等个人信息。故企业支付宝账户背后承载的自然人信息属于“公民个人信息”，属于刑法保护对象。行为人非法出售关联公民个人信息的企业支付宝账户信息，情节严重的，构成侵犯公民个人信息罪。<br/>　　",
        "cpws_al_fyjb_id": "",
        "cpws_al_fyjb_name": "",
        "cpws_al_spnf": "",
        "cpws_al_fbnf": "",
        "cpws_al_fulltext": "",
        "cpws_al_jbaq": "",
        "cpws_al_cpjg": "",
        "cpws_al_cply": "",
        "cpws_al_aljz": "",
        "cpws_al_glsy": "",
        "cpws_al_sub_title": "",
        "cpws_al_is_del": "",
        "cpws_al_infos": "2024-04-1-207-004 / 刑事 / 侵犯公民个人信息罪 / 四川省泸州市中级人民法院 / 2020.11.19 / （2020）川05刑终124号 / 二审 / 入库日期：2024.12.12",
        "cpws_al_fbxx": "",
        "cpws_al_sxcpr": "",
        "cpws_al_pdls": "",
        "sort_num": "27675",
        "cpws_al_add_time": "",
        "cpws_al_rk_time": "2024-12-12 17:34:21",
        "cpws_al_update_time": "",
        "cpws_al_wsxz": "",
        "cpws_al_ts": "04",
        "cpws_al_ts_name": "（刑三庭）",
        "cpws_al_sf": "四川省",
        "cpws_al_source_id": [
          "0101"
        ],
        "cpws_al_lzgc": "",
        "cpws_al_zdyy": "",
        "cpws_al_jdhg_id": "1189238496389234688",
        "ai_score": 0.0,
        "cpws_al_new_zdxal": ""
      }
    ]
  }
}